{
	"id": 7805,
	"name": "pricing-models",
	"variant": "project",
	"kind": 1,
	"flags": {},
	"comment": {
		"summary": [
			{
				"text": "## Relations Overview\n\n",
				"kind": "text"
			},
			{
				"text": "```mermaid\nerDiagram\n\tPrice }|--|{ PriceSet : price_set\n\tPrice ||--|| PriceRule : price_rules\n\tPrice }|--|{ PriceList : price_list\n\tPriceList ||--|| PriceListRule : price_list_rules\n\tPriceList }|--|{ RuleType : rule_types\n\tPriceListRule }|--|{ RuleType : rule_type\n\tPriceListRule ||--|| PriceListRuleValue : price_list_rule_values\n\tPriceRule }|--|{ PriceSet : price_set\n\tPriceRule }|--|{ RuleType : rule_type\n\tPriceSet }|--|{ RuleType : rule_types\n\n```",
				"kind": "code"
			}
		]
	},
	"children": [
		{
			"id": 7868,
			"name": "PriceListRuleValue",
			"variant": "declaration",
			"kind": 128,
			"flags": {},
			"children": [
				{
					"id": 7869,
					"name": "constructor",
					"variant": "declaration",
					"kind": 512,
					"flags": {},
					"signatures": [
						{
							"id": 7870,
							"name": "new PriceListRuleValue",
							"variant": "signature",
							"kind": 16384,
							"flags": {},
							"type": {
								"type": "reference",
								"target": 7868,
								"name": "default",
								"package": "@medusajs/pricing"
							}
						}
					]
				},
				{
					"id": 7882,
					"name": "[OptionalProps]",
					"variant": "declaration",
					"kind": 1024,
					"flags": {
						"isOptional": true
					},
					"type": {
						"type": "reference",
						"target": {
							"sourceFileName": "../../../packages/types/src/dal/entity.ts",
							"qualifiedName": "SoftDeletableEntityDateColumns"
						},
						"name": "SoftDeletableEntityDateColumns",
						"package": "@medusajs/types"
					}
				},
				{
					"id": 7871,
					"name": "id",
					"variant": "declaration",
					"kind": 1024,
					"flags": {},
					"type": {
						"type": "intrinsic",
						"name": "string"
					}
				},
				{
					"id": 7872,
					"name": "price_list_rule_id",
					"variant": "declaration",
					"kind": 1024,
					"flags": {},
					"type": {
						"type": "intrinsic",
						"name": "string"
					}
				},
				{
					"id": 7873,
					"name": "price_list_rule",
					"variant": "declaration",
					"kind": 1024,
					"flags": {},
					"type": {
						"type": "reference",
						"target": 7851,
						"name": "default",
						"package": "@medusajs/pricing"
					}
				},
				{
					"id": 7874,
					"name": "value",
					"variant": "declaration",
					"kind": 1024,
					"flags": {},
					"type": {
						"type": "intrinsic",
						"name": "string"
					}
				},
				{
					"id": 7875,
					"name": "created_at",
					"variant": "declaration",
					"kind": 1024,
					"flags": {},
					"type": {
						"type": "reference",
						"target": {
							"sourceFileName": "../../node_modules/typescript/lib/lib.es5.d.ts",
							"qualifiedName": "Date"
						},
						"name": "Date",
						"package": "typescript"
					}
				},
				{
					"id": 7876,
					"name": "updated_at",
					"variant": "declaration",
					"kind": 1024,
					"flags": {},
					"type": {
						"type": "reference",
						"target": {
							"sourceFileName": "../../node_modules/typescript/lib/lib.es5.d.ts",
							"qualifiedName": "Date"
						},
						"name": "Date",
						"package": "typescript"
					}
				},
				{
					"id": 7877,
					"name": "deleted_at",
					"variant": "declaration",
					"kind": 1024,
					"flags": {},
					"type": {
						"type": "union",
						"types": [
							{
								"type": "literal",
								"value": null
							},
							{
								"type": "reference",
								"target": {
									"sourceFileName": "../../node_modules/typescript/lib/lib.es5.d.ts",
									"qualifiedName": "Date"
								},
								"name": "Date",
								"package": "typescript"
							}
						]
					},
					"defaultValue": "null"
				},
				{
					"id": 7878,
					"name": "onCreate",
					"variant": "declaration",
					"kind": 2048,
					"flags": {},
					"signatures": [
						{
							"id": 7879,
							"name": "onCreate",
							"variant": "signature",
							"kind": 4096,
							"flags": {},
							"type": {
								"type": "intrinsic",
								"name": "void"
							}
						}
					]
				},
				{
					"id": 7880,
					"name": "onInit",
					"variant": "declaration",
					"kind": 2048,
					"flags": {},
					"signatures": [
						{
							"id": 7881,
							"name": "onInit",
							"variant": "signature",
							"kind": 4096,
							"flags": {},
							"type": {
								"type": "intrinsic",
								"name": "void"
							}
						}
					]
				}
			],
			"groups": [
				{
					"title": "Constructors",
					"children": [
						7869
					]
				},
				{
					"title": "Properties",
					"children": [
						7882,
						7871,
						7872,
						7873,
						7874,
						7875,
						7876,
						7877
					]
				},
				{
					"title": "Methods",
					"children": [
						7878,
						7880
					]
				}
			]
		},
		{
			"id": 7851,
			"name": "PriceListRule",
			"variant": "declaration",
			"kind": 128,
			"flags": {},
			"children": [
				{
					"id": 7852,
					"name": "constructor",
					"variant": "declaration",
					"kind": 512,
					"flags": {},
					"signatures": [
						{
							"id": 7853,
							"name": "new PriceListRule",
							"variant": "signature",
							"kind": 16384,
							"flags": {},
							"type": {
								"type": "reference",
								"target": 7851,
								"name": "default",
								"package": "@medusajs/pricing"
							}
						}
					]
				},
				{
					"id": 7867,
					"name": "[OptionalProps]",
					"variant": "declaration",
					"kind": 1024,
					"flags": {},
					"type": {
						"type": "reference",
						"target": {
							"sourceFileName": "../../../packages/types/src/dal/entity.ts",
							"qualifiedName": "SoftDeletableEntityDateColumns"
						},
						"name": "SoftDeletableEntityDateColumns",
						"package": "@medusajs/types"
					}
				},
				{
					"id": 7854,
					"name": "id",
					"variant": "declaration",
					"kind": 1024,
					"flags": {},
					"type": {
						"type": "intrinsic",
						"name": "string"
					}
				},
				{
					"id": 7855,
					"name": "rule_type_id",
					"variant": "declaration",
					"kind": 1024,
					"flags": {},
					"type": {
						"type": "intrinsic",
						"name": "string"
					}
				},
				{
					"id": 7856,
					"name": "rule_type",
					"variant": "declaration",
					"kind": 1024,
					"flags": {},
					"type": {
						"type": "reference",
						"target": 7930,
						"name": "RuleType",
						"package": "@medusajs/pricing"
					}
				},
				{
					"id": 7857,
					"name": "price_list_rule_values",
					"variant": "declaration",
					"kind": 1024,
					"flags": {},
					"type": {
						"type": "reference",
						"target": {
							"sourceFileName": "../../../node_modules/@mikro-orm/core/entity/Collection.d.ts",
							"qualifiedName": "Collection"
						},
						"typeArguments": [
							{
								"type": "reference",
								"target": 7868,
								"name": "default",
								"package": "@medusajs/pricing"
							},
							{
								"type": "intrinsic",
								"name": "object"
							}
						],
						"name": "Collection",
						"package": "@mikro-orm/core"
					},
					"defaultValue": "..."
				},
				{
					"id": 7858,
					"name": "price_list_id",
					"variant": "declaration",
					"kind": 1024,
					"flags": {},
					"type": {
						"type": "intrinsic",
						"name": "string"
					}
				},
				{
					"id": 7859,
					"name": "price_list",
					"variant": "declaration",
					"kind": 1024,
					"flags": {},
					"type": {
						"type": "reference",
						"target": 7829,
						"name": "default",
						"package": "@medusajs/pricing"
					}
				},
				{
					"id": 7860,
					"name": "created_at",
					"variant": "declaration",
					"kind": 1024,
					"flags": {},
					"type": {
						"type": "reference",
						"target": {
							"sourceFileName": "../../node_modules/typescript/lib/lib.es5.d.ts",
							"qualifiedName": "Date"
						},
						"name": "Date",
						"package": "typescript"
					}
				},
				{
					"id": 7861,
					"name": "updated_at",
					"variant": "declaration",
					"kind": 1024,
					"flags": {},
					"type": {
						"type": "reference",
						"target": {
							"sourceFileName": "../../node_modules/typescript/lib/lib.es5.d.ts",
							"qualifiedName": "Date"
						},
						"name": "Date",
						"package": "typescript"
					}
				},
				{
					"id": 7862,
					"name": "deleted_at",
					"variant": "declaration",
					"kind": 1024,
					"flags": {},
					"type": {
						"type": "union",
						"types": [
							{
								"type": "literal",
								"value": null
							},
							{
								"type": "reference",
								"target": {
									"sourceFileName": "../../node_modules/typescript/lib/lib.es5.d.ts",
									"qualifiedName": "Date"
								},
								"name": "Date",
								"package": "typescript"
							}
						]
					},
					"defaultValue": "null"
				},
				{
					"id": 7863,
					"name": "beforeCreate",
					"variant": "declaration",
					"kind": 2048,
					"flags": {},
					"signatures": [
						{
							"id": 7864,
							"name": "beforeCreate",
							"variant": "signature",
							"kind": 4096,
							"flags": {},
							"type": {
								"type": "intrinsic",
								"name": "void"
							}
						}
					]
				},
				{
					"id": 7865,
					"name": "onInit",
					"variant": "declaration",
					"kind": 2048,
					"flags": {},
					"signatures": [
						{
							"id": 7866,
							"name": "onInit",
							"variant": "signature",
							"kind": 4096,
							"flags": {},
							"type": {
								"type": "intrinsic",
								"name": "void"
							}
						}
					]
				}
			],
			"groups": [
				{
					"title": "Constructors",
					"children": [
						7852
					]
				},
				{
					"title": "Properties",
					"children": [
						7867,
						7854,
						7855,
						7856,
						7857,
						7858,
						7859,
						7860,
						7861,
						7862
					]
				},
				{
					"title": "Methods",
					"children": [
						7863,
						7865
					]
				}
			]
		},
		{
			"id": 7829,
			"name": "PriceList",
			"variant": "declaration",
			"kind": 128,
			"flags": {},
			"children": [
				{
					"id": 7830,
					"name": "constructor",
					"variant": "declaration",
					"kind": 512,
					"flags": {},
					"signatures": [
						{
							"id": 7831,
							"name": "new PriceList",
							"variant": "signature",
							"kind": 16384,
							"flags": {},
							"type": {
								"type": "reference",
								"target": 7829,
								"name": "default",
								"package": "@medusajs/pricing"
							}
						}
					]
				},
				{
					"id": 7850,
					"name": "[OptionalProps]",
					"variant": "declaration",
					"kind": 1024,
					"flags": {},
					"type": {
						"type": "reference",
						"target": {
							"sourceFileName": "../../../packages/pricing/src/models/price-list.ts",
							"qualifiedName": "OptionalFields"
						},
						"name": "OptionalFields",
						"package": "@medusajs/pricing"
					}
				},
				{
					"id": 7832,
					"name": "id",
					"variant": "declaration",
					"kind": 1024,
					"flags": {},
					"type": {
						"type": "intrinsic",
						"name": "string"
					}
				},
				{
					"id": 7833,
					"name": "title",
					"variant": "declaration",
					"kind": 1024,
					"flags": {},
					"type": {
						"type": "intrinsic",
						"name": "string"
					}
				},
				{
					"id": 7834,
					"name": "description",
					"variant": "declaration",
					"kind": 1024,
					"flags": {},
					"type": {
						"type": "intrinsic",
						"name": "string"
					}
				},
				{
					"id": 7835,
					"name": "status",
					"variant": "declaration",
					"kind": 1024,
					"flags": {},
					"type": {
						"type": "reference",
						"target": {
							"sourceFileName": "../../../packages/utils/dist/pricing/price-list.d.ts",
							"qualifiedName": "PriceListStatus"
						},
						"name": "PriceListStatus",
						"package": "@medusajs/utils"
					}
				},
				{
					"id": 7836,
					"name": "type",
					"variant": "declaration",
					"kind": 1024,
					"flags": {},
					"type": {
						"type": "reference",
						"target": {
							"sourceFileName": "../../../packages/utils/dist/pricing/price-list.d.ts",
							"qualifiedName": "PriceListType"
						},
						"name": "PriceListType",
						"package": "@medusajs/utils"
					}
				},
				{
					"id": 7837,
					"name": "starts_at",
					"variant": "declaration",
					"kind": 1024,
					"flags": {},
					"type": {
						"type": "union",
						"types": [
							{
								"type": "literal",
								"value": null
							},
							{
								"type": "reference",
								"target": {
									"sourceFileName": "../../node_modules/typescript/lib/lib.es5.d.ts",
									"qualifiedName": "Date"
								},
								"name": "Date",
								"package": "typescript"
							}
						]
					},
					"defaultValue": "null"
				},
				{
					"id": 7838,
					"name": "ends_at",
					"variant": "declaration",
					"kind": 1024,
					"flags": {},
					"type": {
						"type": "union",
						"types": [
							{
								"type": "literal",
								"value": null
							},
							{
								"type": "reference",
								"target": {
									"sourceFileName": "../../node_modules/typescript/lib/lib.es5.d.ts",
									"qualifiedName": "Date"
								},
								"name": "Date",
								"package": "typescript"
							}
						]
					},
					"defaultValue": "null"
				},
				{
					"id": 7839,
					"name": "prices",
					"variant": "declaration",
					"kind": 1024,
					"flags": {},
					"type": {
						"type": "reference",
						"target": {
							"sourceFileName": "../../../node_modules/@mikro-orm/core/entity/Collection.d.ts",
							"qualifiedName": "Collection"
						},
						"typeArguments": [
							{
								"type": "reference",
								"target": 7806,
								"name": "default",
								"package": "@medusajs/pricing"
							},
							{
								"type": "intrinsic",
								"name": "object"
							}
						],
						"name": "Collection",
						"package": "@mikro-orm/core"
					},
					"defaultValue": "..."
				},
				{
					"id": 7840,
					"name": "price_list_rules",
					"variant": "declaration",
					"kind": 1024,
					"flags": {},
					"type": {
						"type": "reference",
						"target": {
							"sourceFileName": "../../../node_modules/@mikro-orm/core/entity/Collection.d.ts",
							"qualifiedName": "Collection"
						},
						"typeArguments": [
							{
								"type": "reference",
								"target": 7851,
								"name": "default",
								"package": "@medusajs/pricing"
							},
							{
								"type": "intrinsic",
								"name": "object"
							}
						],
						"name": "Collection",
						"package": "@mikro-orm/core"
					},
					"defaultValue": "..."
				},
				{
					"id": 7841,
					"name": "rule_types",
					"variant": "declaration",
					"kind": 1024,
					"flags": {},
					"type": {
						"type": "reference",
						"target": {
							"sourceFileName": "../../../node_modules/@mikro-orm/core/entity/Collection.d.ts",
							"qualifiedName": "Collection"
						},
						"typeArguments": [
							{
								"type": "reference",
								"target": 7930,
								"name": "RuleType",
								"package": "@medusajs/pricing"
							},
							{
								"type": "intrinsic",
								"name": "object"
							}
						],
						"name": "Collection",
						"package": "@mikro-orm/core"
					},
					"defaultValue": "..."
				},
				{
					"id": 7842,
					"name": "rules_count",
					"variant": "declaration",
					"kind": 1024,
					"flags": {},
					"type": {
						"type": "intrinsic",
						"name": "number"
					},
					"defaultValue": "0"
				},
				{
					"id": 7843,
					"name": "created_at",
					"variant": "declaration",
					"kind": 1024,
					"flags": {},
					"type": {
						"type": "reference",
						"target": {
							"sourceFileName": "../../node_modules/typescript/lib/lib.es5.d.ts",
							"qualifiedName": "Date"
						},
						"name": "Date",
						"package": "typescript"
					}
				},
				{
					"id": 7844,
					"name": "updated_at",
					"variant": "declaration",
					"kind": 1024,
					"flags": {},
					"type": {
						"type": "reference",
						"target": {
							"sourceFileName": "../../node_modules/typescript/lib/lib.es5.d.ts",
							"qualifiedName": "Date"
						},
						"name": "Date",
						"package": "typescript"
					}
				},
				{
					"id": 7845,
					"name": "deleted_at",
					"variant": "declaration",
					"kind": 1024,
					"flags": {},
					"type": {
						"type": "union",
						"types": [
							{
								"type": "literal",
								"value": null
							},
							{
								"type": "reference",
								"target": {
									"sourceFileName": "../../node_modules/typescript/lib/lib.es5.d.ts",
									"qualifiedName": "Date"
								},
								"name": "Date",
								"package": "typescript"
							}
						]
					},
					"defaultValue": "null"
				},
				{
					"id": 7846,
					"name": "onCreate",
					"variant": "declaration",
					"kind": 2048,
					"flags": {},
					"signatures": [
						{
							"id": 7847,
							"name": "onCreate",
							"variant": "signature",
							"kind": 4096,
							"flags": {},
							"type": {
								"type": "intrinsic",
								"name": "void"
							}
						}
					]
				},
				{
					"id": 7848,
					"name": "onInit",
					"variant": "declaration",
					"kind": 2048,
					"flags": {},
					"signatures": [
						{
							"id": 7849,
							"name": "onInit",
							"variant": "signature",
							"kind": 4096,
							"flags": {},
							"type": {
								"type": "intrinsic",
								"name": "void"
							}
						}
					]
				}
			],
			"groups": [
				{
					"title": "Constructors",
					"children": [
						7830
					]
				},
				{
					"title": "Properties",
					"children": [
						7850,
						7832,
						7833,
						7834,
						7835,
						7836,
						7837,
						7838,
						7839,
						7840,
						7841,
						7842,
						7843,
						7844,
						7845
					]
				},
				{
					"title": "Methods",
					"children": [
						7846,
						7848
					]
				}
			]
		},
		{
			"id": 7883,
			"name": "PriceRule",
			"variant": "declaration",
			"kind": 128,
			"flags": {},
			"children": [
				{
					"id": 7884,
					"name": "constructor",
					"variant": "declaration",
					"kind": 512,
					"flags": {},
					"signatures": [
						{
							"id": 7885,
							"name": "new PriceRule",
							"variant": "signature",
							"kind": 16384,
							"flags": {},
							"type": {
								"type": "reference",
								"target": 7883,
								"name": "default",
								"package": "@medusajs/pricing"
							}
						}
					]
				},
				{
					"id": 7902,
					"name": "[OptionalProps]",
					"variant": "declaration",
					"kind": 1024,
					"flags": {
						"isOptional": true
					},
					"type": {
						"type": "reference",
						"target": {
							"sourceFileName": "../../../packages/types/src/dal/entity.ts",
							"qualifiedName": "SoftDeletableEntityDateColumns"
						},
						"name": "SoftDeletableEntityDateColumns",
						"package": "@medusajs/types"
					}
				},
				{
					"id": 7886,
					"name": "id",
					"variant": "declaration",
					"kind": 1024,
					"flags": {},
					"type": {
						"type": "intrinsic",
						"name": "string"
					}
				},
				{
					"id": 7887,
					"name": "price_set_id",
					"variant": "declaration",
					"kind": 1024,
					"flags": {},
					"type": {
						"type": "intrinsic",
						"name": "string"
					}
				},
				{
					"id": 7888,
					"name": "price_set",
					"variant": "declaration",
					"kind": 1024,
					"flags": {},
					"type": {
						"type": "reference",
						"target": 7903,
						"name": "default",
						"package": "@medusajs/pricing"
					}
				},
				{
					"id": 7889,
					"name": "rule_type_id",
					"variant": "declaration",
					"kind": 1024,
					"flags": {},
					"type": {
						"type": "intrinsic",
						"name": "string"
					}
				},
				{
					"id": 7890,
					"name": "rule_type",
					"variant": "declaration",
					"kind": 1024,
					"flags": {},
					"type": {
						"type": "reference",
						"target": 7930,
						"name": "RuleType",
						"package": "@medusajs/pricing"
					}
				},
				{
					"id": 7891,
					"name": "value",
					"variant": "declaration",
					"kind": 1024,
					"flags": {},
					"type": {
						"type": "intrinsic",
						"name": "string"
					}
				},
				{
					"id": 7892,
					"name": "priority",
					"variant": "declaration",
					"kind": 1024,
					"flags": {},
					"type": {
						"type": "intrinsic",
						"name": "number"
					},
					"defaultValue": "0"
				},
				{
					"id": 7893,
					"name": "price_id",
					"variant": "declaration",
					"kind": 1024,
					"flags": {},
					"type": {
						"type": "intrinsic",
						"name": "string"
					}
				},
				{
					"id": 7894,
					"name": "price",
					"variant": "declaration",
					"kind": 1024,
					"flags": {},
					"type": {
						"type": "reference",
						"target": 7806,
						"name": "default",
						"package": "@medusajs/pricing"
					}
				},
				{
					"id": 7895,
					"name": "created_at",
					"variant": "declaration",
					"kind": 1024,
					"flags": {},
					"type": {
						"type": "reference",
						"target": {
							"sourceFileName": "../../node_modules/typescript/lib/lib.es5.d.ts",
							"qualifiedName": "Date"
						},
						"name": "Date",
						"package": "typescript"
					}
				},
				{
					"id": 7896,
					"name": "updated_at",
					"variant": "declaration",
					"kind": 1024,
					"flags": {},
					"type": {
						"type": "reference",
						"target": {
							"sourceFileName": "../../node_modules/typescript/lib/lib.es5.d.ts",
							"qualifiedName": "Date"
						},
						"name": "Date",
						"package": "typescript"
					}
				},
				{
					"id": 7897,
					"name": "deleted_at",
					"variant": "declaration",
					"kind": 1024,
					"flags": {},
					"type": {
						"type": "union",
						"types": [
							{
								"type": "literal",
								"value": null
							},
							{
								"type": "reference",
								"target": {
									"sourceFileName": "../../node_modules/typescript/lib/lib.es5.d.ts",
									"qualifiedName": "Date"
								},
								"name": "Date",
								"package": "typescript"
							}
						]
					},
					"defaultValue": "null"
				},
				{
					"id": 7898,
					"name": "beforeCreate",
					"variant": "declaration",
					"kind": 2048,
					"flags": {},
					"signatures": [
						{
							"id": 7899,
							"name": "beforeCreate",
							"variant": "signature",
							"kind": 4096,
							"flags": {},
							"type": {
								"type": "intrinsic",
								"name": "void"
							}
						}
					]
				},
				{
					"id": 7900,
					"name": "onInit",
					"variant": "declaration",
					"kind": 2048,
					"flags": {},
					"signatures": [
						{
							"id": 7901,
							"name": "onInit",
							"variant": "signature",
							"kind": 4096,
							"flags": {},
							"type": {
								"type": "intrinsic",
								"name": "void"
							}
						}
					]
				}
			],
			"groups": [
				{
					"title": "Constructors",
					"children": [
						7884
					]
				},
				{
					"title": "Properties",
					"children": [
						7902,
						7886,
						7887,
						7888,
						7889,
						7890,
						7891,
						7892,
						7893,
						7894,
						7895,
						7896,
						7897
					]
				},
				{
					"title": "Methods",
					"children": [
						7898,
						7900
					]
				}
			]
		},
		{
			"id": 7917,
			"name": "PriceSetRuleType",
			"variant": "declaration",
			"kind": 128,
			"flags": {},
			"children": [
				{
					"id": 7918,
					"name": "constructor",
					"variant": "declaration",
					"kind": 512,
					"flags": {},
					"signatures": [
						{
							"id": 7919,
							"name": "new PriceSetRuleType",
							"variant": "signature",
							"kind": 16384,
							"flags": {},
							"type": {
								"type": "reference",
								"target": 7917,
								"name": "default",
								"package": "@medusajs/pricing"
							}
						}
					]
				},
				{
					"id": 7920,
					"name": "id",
					"variant": "declaration",
					"kind": 1024,
					"flags": {},
					"type": {
						"type": "intrinsic",
						"name": "string"
					}
				},
				{
					"id": 7921,
					"name": "price_set_id",
					"variant": "declaration",
					"kind": 1024,
					"flags": {},
					"type": {
						"type": "intrinsic",
						"name": "string"
					}
				},
				{
					"id": 7922,
					"name": "rule_type_id",
					"variant": "declaration",
					"kind": 1024,
					"flags": {},
					"type": {
						"type": "intrinsic",
						"name": "string"
					}
				},
				{
					"id": 7923,
					"name": "created_at",
					"variant": "declaration",
					"kind": 1024,
					"flags": {},
					"type": {
						"type": "reference",
						"target": {
							"sourceFileName": "../../node_modules/typescript/lib/lib.es5.d.ts",
							"qualifiedName": "Date"
						},
						"name": "Date",
						"package": "typescript"
					}
				},
				{
					"id": 7924,
					"name": "updated_at",
					"variant": "declaration",
					"kind": 1024,
					"flags": {},
					"type": {
						"type": "reference",
						"target": {
							"sourceFileName": "../../node_modules/typescript/lib/lib.es5.d.ts",
							"qualifiedName": "Date"
						},
						"name": "Date",
						"package": "typescript"
					}
				},
				{
					"id": 7925,
					"name": "deleted_at",
					"variant": "declaration",
					"kind": 1024,
					"flags": {},
					"type": {
						"type": "union",
						"types": [
							{
								"type": "literal",
								"value": null
							},
							{
								"type": "reference",
								"target": {
									"sourceFileName": "../../node_modules/typescript/lib/lib.es5.d.ts",
									"qualifiedName": "Date"
								},
								"name": "Date",
								"package": "typescript"
							}
						]
					},
					"defaultValue": "null"
				},
				{
					"id": 7926,
					"name": "onCreate",
					"variant": "declaration",
					"kind": 2048,
					"flags": {},
					"signatures": [
						{
							"id": 7927,
							"name": "onCreate",
							"variant": "signature",
							"kind": 4096,
							"flags": {},
							"type": {
								"type": "intrinsic",
								"name": "void"
							}
						}
					]
				},
				{
					"id": 7928,
					"name": "onInit",
					"variant": "declaration",
					"kind": 2048,
					"flags": {},
					"signatures": [
						{
							"id": 7929,
							"name": "onInit",
							"variant": "signature",
							"kind": 4096,
							"flags": {},
							"type": {
								"type": "intrinsic",
								"name": "void"
							}
						}
					]
				}
			],
			"groups": [
				{
					"title": "Constructors",
					"children": [
						7918
					]
				},
				{
					"title": "Properties",
					"children": [
						7920,
						7921,
						7922,
						7923,
						7924,
						7925
					]
				},
				{
					"title": "Methods",
					"children": [
						7926,
						7928
					]
				}
			]
		},
		{
			"id": 7903,
			"name": "PriceSet",
			"variant": "declaration",
			"kind": 128,
			"flags": {},
			"children": [
				{
					"id": 7904,
					"name": "constructor",
					"variant": "declaration",
					"kind": 512,
					"flags": {},
					"signatures": [
						{
							"id": 7905,
							"name": "new PriceSet",
							"variant": "signature",
							"kind": 16384,
							"flags": {},
							"type": {
								"type": "reference",
								"target": 7903,
								"name": "default",
								"package": "@medusajs/pricing"
							}
						}
					]
				},
				{
					"id": 7906,
					"name": "id",
					"variant": "declaration",
					"kind": 1024,
					"flags": {},
					"type": {
						"type": "intrinsic",
						"name": "string"
					}
				},
				{
					"id": 7907,
					"name": "prices",
					"variant": "declaration",
					"kind": 1024,
					"flags": {},
					"type": {
						"type": "reference",
						"target": {
							"sourceFileName": "../../../node_modules/@mikro-orm/core/entity/Collection.d.ts",
							"qualifiedName": "Collection"
						},
						"typeArguments": [
							{
								"type": "reference",
								"target": 7806,
								"name": "default",
								"package": "@medusajs/pricing"
							},
							{
								"type": "intrinsic",
								"name": "object"
							}
						],
						"name": "Collection",
						"package": "@mikro-orm/core"
					},
					"defaultValue": "..."
				},
				{
					"id": 7908,
					"name": "price_rules",
					"variant": "declaration",
					"kind": 1024,
					"flags": {},
					"type": {
						"type": "reference",
						"target": {
							"sourceFileName": "../../../node_modules/@mikro-orm/core/entity/Collection.d.ts",
							"qualifiedName": "Collection"
						},
						"typeArguments": [
							{
								"type": "reference",
								"target": 7883,
								"name": "default",
								"package": "@medusajs/pricing"
							},
							{
								"type": "intrinsic",
								"name": "object"
							}
						],
						"name": "Collection",
						"package": "@mikro-orm/core"
					},
					"defaultValue": "..."
				},
				{
					"id": 7909,
					"name": "rule_types",
					"variant": "declaration",
					"kind": 1024,
					"flags": {},
					"type": {
						"type": "reference",
						"target": {
							"sourceFileName": "../../../node_modules/@mikro-orm/core/entity/Collection.d.ts",
							"qualifiedName": "Collection"
						},
						"typeArguments": [
							{
								"type": "reference",
								"target": 7930,
								"name": "RuleType",
								"package": "@medusajs/pricing"
							},
							{
								"type": "intrinsic",
								"name": "object"
							}
						],
						"name": "Collection",
						"package": "@mikro-orm/core"
					},
					"defaultValue": "..."
				},
				{
					"id": 7910,
					"name": "created_at",
					"variant": "declaration",
					"kind": 1024,
					"flags": {},
					"type": {
						"type": "reference",
						"target": {
							"sourceFileName": "../../node_modules/typescript/lib/lib.es5.d.ts",
							"qualifiedName": "Date"
						},
						"name": "Date",
						"package": "typescript"
					}
				},
				{
					"id": 7911,
					"name": "updated_at",
					"variant": "declaration",
					"kind": 1024,
					"flags": {},
					"type": {
						"type": "reference",
						"target": {
							"sourceFileName": "../../node_modules/typescript/lib/lib.es5.d.ts",
							"qualifiedName": "Date"
						},
						"name": "Date",
						"package": "typescript"
					}
				},
				{
					"id": 7912,
					"name": "deleted_at",
					"variant": "declaration",
					"kind": 1024,
					"flags": {},
					"type": {
						"type": "union",
						"types": [
							{
								"type": "literal",
								"value": null
							},
							{
								"type": "reference",
								"target": {
									"sourceFileName": "../../node_modules/typescript/lib/lib.es5.d.ts",
									"qualifiedName": "Date"
								},
								"name": "Date",
								"package": "typescript"
							}
						]
					},
					"defaultValue": "null"
				},
				{
					"id": 7913,
					"name": "onCreate",
					"variant": "declaration",
					"kind": 2048,
					"flags": {},
					"signatures": [
						{
							"id": 7914,
							"name": "onCreate",
							"variant": "signature",
							"kind": 4096,
							"flags": {},
							"type": {
								"type": "intrinsic",
								"name": "void"
							}
						}
					]
				},
				{
					"id": 7915,
					"name": "onInit",
					"variant": "declaration",
					"kind": 2048,
					"flags": {},
					"signatures": [
						{
							"id": 7916,
							"name": "onInit",
							"variant": "signature",
							"kind": 4096,
							"flags": {},
							"type": {
								"type": "intrinsic",
								"name": "void"
							}
						}
					]
				}
			],
			"groups": [
				{
					"title": "Constructors",
					"children": [
						7904
					]
				},
				{
					"title": "Properties",
					"children": [
						7906,
						7907,
						7908,
						7909,
						7910,
						7911,
						7912
					]
				},
				{
					"title": "Methods",
					"children": [
						7913,
						7915
					]
				}
			]
		},
		{
			"id": 7806,
			"name": "Price",
			"variant": "declaration",
			"kind": 128,
			"flags": {},
			"children": [
				{
					"id": 7807,
					"name": "constructor",
					"variant": "declaration",
					"kind": 512,
					"flags": {},
					"signatures": [
						{
							"id": 7808,
							"name": "new Price",
							"variant": "signature",
							"kind": 16384,
							"flags": {},
							"type": {
								"type": "reference",
								"target": 7806,
								"name": "default",
								"package": "@medusajs/pricing"
							}
						}
					]
				},
				{
					"id": 7828,
					"name": "[OptionalProps]",
					"variant": "declaration",
					"kind": 1024,
					"flags": {
						"isOptional": true
					},
					"type": {
						"type": "reference",
						"target": {
							"sourceFileName": "../../../packages/types/src/dal/entity.ts",
							"qualifiedName": "SoftDeletableEntityDateColumns"
						},
						"name": "SoftDeletableEntityDateColumns",
						"package": "@medusajs/types"
					}
				},
				{
					"id": 7809,
					"name": "id",
					"variant": "declaration",
					"kind": 1024,
					"flags": {},
					"type": {
						"type": "intrinsic",
						"name": "string"
					}
				},
				{
					"id": 7810,
					"name": "title",
					"variant": "declaration",
					"kind": 1024,
					"flags": {},
					"type": {
						"type": "union",
						"types": [
							{
								"type": "literal",
								"value": null
							},
							{
								"type": "intrinsic",
								"name": "string"
							}
						]
					},
					"defaultValue": "null"
				},
				{
					"id": 7811,
					"name": "currency_code",
					"variant": "declaration",
					"kind": 1024,
					"flags": {},
					"type": {
						"type": "intrinsic",
						"name": "string"
					}
				},
				{
					"id": 7812,
					"name": "amount",
					"variant": "declaration",
					"kind": 1024,
					"flags": {},
					"type": {
						"type": "intrinsic",
						"name": "number"
					}
				},
				{
					"id": 7813,
					"name": "min_quantity",
					"variant": "declaration",
					"kind": 1024,
					"flags": {},
					"type": {
						"type": "union",
						"types": [
							{
								"type": "literal",
								"value": null
							},
							{
								"type": "intrinsic",
								"name": "number"
							}
						]
					},
					"defaultValue": "null"
				},
				{
					"id": 7814,
					"name": "max_quantity",
					"variant": "declaration",
					"kind": 1024,
					"flags": {},
					"type": {
						"type": "union",
						"types": [
							{
								"type": "literal",
								"value": null
							},
							{
								"type": "intrinsic",
								"name": "number"
							}
						]
					},
					"defaultValue": "null"
				},
				{
					"id": 7815,
					"name": "price_set_id",
					"variant": "declaration",
					"kind": 1024,
					"flags": {},
					"type": {
						"type": "intrinsic",
						"name": "string"
					}
				},
				{
					"id": 7816,
					"name": "price_set",
					"variant": "declaration",
					"kind": 1024,
					"flags": {
						"isOptional": true
					},
					"type": {
						"type": "reference",
						"target": 7903,
						"name": "default",
						"package": "@medusajs/pricing"
					}
				},
				{
					"id": 7817,
					"name": "rules_count",
					"variant": "declaration",
					"kind": 1024,
					"flags": {},
					"type": {
						"type": "intrinsic",
						"name": "number"
					},
					"defaultValue": "0"
				},
				{
					"id": 7818,
					"name": "price_rules",
					"variant": "declaration",
					"kind": 1024,
					"flags": {},
					"type": {
						"type": "reference",
						"target": {
							"sourceFileName": "../../../node_modules/@mikro-orm/core/entity/Collection.d.ts",
							"qualifiedName": "Collection"
						},
						"typeArguments": [
							{
								"type": "reference",
								"target": 7883,
								"name": "default",
								"package": "@medusajs/pricing"
							},
							{
								"type": "intrinsic",
								"name": "object"
							}
						],
						"name": "Collection",
						"package": "@mikro-orm/core"
					},
					"defaultValue": "..."
				},
				{
					"id": 7819,
					"name": "price_list_id",
					"variant": "declaration",
					"kind": 1024,
					"flags": {},
					"type": {
						"type": "union",
						"types": [
							{
								"type": "literal",
								"value": null
							},
							{
								"type": "intrinsic",
								"name": "string"
							}
						]
					},
					"defaultValue": "null"
				},
				{
					"id": 7820,
					"name": "price_list",
					"variant": "declaration",
					"kind": 1024,
					"flags": {},
					"type": {
						"type": "union",
						"types": [
							{
								"type": "literal",
								"value": null
							},
							{
								"type": "reference",
								"target": 7829,
								"name": "default",
								"package": "@medusajs/pricing"
							}
						]
					},
					"defaultValue": "null"
				},
				{
					"id": 7821,
					"name": "created_at",
					"variant": "declaration",
					"kind": 1024,
					"flags": {},
					"type": {
						"type": "reference",
						"target": {
							"sourceFileName": "../../node_modules/typescript/lib/lib.es5.d.ts",
							"qualifiedName": "Date"
						},
						"name": "Date",
						"package": "typescript"
					}
				},
				{
					"id": 7822,
					"name": "updated_at",
					"variant": "declaration",
					"kind": 1024,
					"flags": {},
					"type": {
						"type": "reference",
						"target": {
							"sourceFileName": "../../node_modules/typescript/lib/lib.es5.d.ts",
							"qualifiedName": "Date"
						},
						"name": "Date",
						"package": "typescript"
					}
				},
				{
					"id": 7823,
					"name": "deleted_at",
					"variant": "declaration",
					"kind": 1024,
					"flags": {},
					"type": {
						"type": "union",
						"types": [
							{
								"type": "literal",
								"value": null
							},
							{
								"type": "reference",
								"target": {
									"sourceFileName": "../../node_modules/typescript/lib/lib.es5.d.ts",
									"qualifiedName": "Date"
								},
								"name": "Date",
								"package": "typescript"
							}
						]
					},
					"defaultValue": "null"
				},
				{
					"id": 7824,
					"name": "onCreate",
					"variant": "declaration",
					"kind": 2048,
					"flags": {},
					"signatures": [
						{
							"id": 7825,
							"name": "onCreate",
							"variant": "signature",
							"kind": 4096,
							"flags": {},
							"type": {
								"type": "intrinsic",
								"name": "void"
							}
						}
					]
				},
				{
					"id": 7826,
					"name": "onInit",
					"variant": "declaration",
					"kind": 2048,
					"flags": {},
					"signatures": [
						{
							"id": 7827,
							"name": "onInit",
							"variant": "signature",
							"kind": 4096,
							"flags": {},
							"type": {
								"type": "intrinsic",
								"name": "void"
							}
						}
					]
				}
			],
			"groups": [
				{
					"title": "Constructors",
					"children": [
						7807
					]
				},
				{
					"title": "Properties",
					"children": [
						7828,
						7809,
						7810,
						7811,
						7812,
						7813,
						7814,
						7815,
						7816,
						7817,
						7818,
						7819,
						7820,
						7821,
						7822,
						7823
					]
				},
				{
					"title": "Methods",
					"children": [
						7824,
						7826
					]
				}
			]
		},
		{
			"id": 7930,
			"name": "RuleType",
			"variant": "declaration",
			"kind": 128,
			"flags": {},
			"children": [
				{
					"id": 7931,
					"name": "constructor",
					"variant": "declaration",
					"kind": 512,
					"flags": {},
					"signatures": [
						{
							"id": 7932,
							"name": "new RuleType",
							"variant": "signature",
							"kind": 16384,
							"flags": {},
							"type": {
								"type": "reference",
								"target": 7930,
								"name": "RuleType",
								"package": "@medusajs/pricing"
							}
						}
					]
				},
				{
					"id": 7945,
					"name": "[OptionalProps]",
					"variant": "declaration",
					"kind": 1024,
					"flags": {
						"isOptional": true
					},
					"type": {
						"type": "literal",
						"value": "default_priority"
					}
				},
				{
					"id": 7933,
					"name": "id",
					"variant": "declaration",
					"kind": 1024,
					"flags": {},
					"type": {
						"type": "intrinsic",
						"name": "string"
					}
				},
				{
					"id": 7934,
					"name": "name",
					"variant": "declaration",
					"kind": 1024,
					"flags": {},
					"type": {
						"type": "intrinsic",
						"name": "string"
					}
				},
				{
					"id": 7935,
					"name": "rule_attribute",
					"variant": "declaration",
					"kind": 1024,
					"flags": {},
					"type": {
						"type": "intrinsic",
						"name": "string"
					}
				},
				{
					"id": 7936,
					"name": "default_priority",
					"variant": "declaration",
					"kind": 1024,
					"flags": {},
					"type": {
						"type": "intrinsic",
						"name": "number"
					}
				},
				{
					"id": 7937,
					"name": "price_sets",
					"variant": "declaration",
					"kind": 1024,
					"flags": {},
					"type": {
						"type": "reference",
						"target": {
							"sourceFileName": "../../../node_modules/@mikro-orm/core/entity/Collection.d.ts",
							"qualifiedName": "Collection"
						},
						"typeArguments": [
							{
								"type": "reference",
								"target": 7903,
								"name": "default",
								"package": "@medusajs/pricing"
							},
							{
								"type": "intrinsic",
								"name": "object"
							}
						],
						"name": "Collection",
						"package": "@mikro-orm/core"
					},
					"defaultValue": "..."
				},
				{
					"id": 7938,
					"name": "created_at",
					"variant": "declaration",
					"kind": 1024,
					"flags": {},
					"type": {
						"type": "reference",
						"target": {
							"sourceFileName": "../../node_modules/typescript/lib/lib.es5.d.ts",
							"qualifiedName": "Date"
						},
						"name": "Date",
						"package": "typescript"
					}
				},
				{
					"id": 7939,
					"name": "updated_at",
					"variant": "declaration",
					"kind": 1024,
					"flags": {},
					"type": {
						"type": "reference",
						"target": {
							"sourceFileName": "../../node_modules/typescript/lib/lib.es5.d.ts",
							"qualifiedName": "Date"
						},
						"name": "Date",
						"package": "typescript"
					}
				},
				{
					"id": 7940,
					"name": "deleted_at",
					"variant": "declaration",
					"kind": 1024,
					"flags": {},
					"type": {
						"type": "union",
						"types": [
							{
								"type": "literal",
								"value": null
							},
							{
								"type": "reference",
								"target": {
									"sourceFileName": "../../node_modules/typescript/lib/lib.es5.d.ts",
									"qualifiedName": "Date"
								},
								"name": "Date",
								"package": "typescript"
							}
						]
					},
					"defaultValue": "null"
				},
				{
					"id": 7941,
					"name": "onCreate",
					"variant": "declaration",
					"kind": 2048,
					"flags": {},
					"signatures": [
						{
							"id": 7942,
							"name": "onCreate",
							"variant": "signature",
							"kind": 4096,
							"flags": {},
							"type": {
								"type": "intrinsic",
								"name": "void"
							}
						}
					]
				},
				{
					"id": 7943,
					"name": "onInit",
					"variant": "declaration",
					"kind": 2048,
					"flags": {},
					"signatures": [
						{
							"id": 7944,
							"name": "onInit",
							"variant": "signature",
							"kind": 4096,
							"flags": {},
							"type": {
								"type": "intrinsic",
								"name": "void"
							}
						}
					]
				}
			],
			"groups": [
				{
					"title": "Constructors",
					"children": [
						7931
					]
				},
				{
					"title": "Properties",
					"children": [
						7945,
						7933,
						7934,
						7935,
						7936,
						7937,
						7938,
						7939,
						7940
					]
				},
				{
					"title": "Methods",
					"children": [
						7941,
						7943
					]
				}
			]
		}
	],
	"groups": [
		{
			"title": "Classes",
			"children": [
				7868,
				7851,
				7829,
				7883,
				7917,
				7903,
				7806,
				7930
			]
		}
	],
	"packageName": "@medusajs/pricing",
	"symbolIdMap": {
		"7805": {
			"sourceFileName": "../../../packages/pricing/src/models/index.ts",
			"qualifiedName": ""
		},
		"7806": {
			"sourceFileName": "../../../packages/pricing/src/models/price.ts",
			"qualifiedName": "default"
		},
		"7809": {
			"sourceFileName": "../../../packages/pricing/src/models/price.ts",
			"qualifiedName": "default.id"
		},
		"7810": {
			"sourceFileName": "../../../packages/pricing/src/models/price.ts",
			"qualifiedName": "default.title"
		},
		"7811": {
			"sourceFileName": "../../../packages/pricing/src/models/price.ts",
			"qualifiedName": "default.currency_code"
		},
		"7812": {
			"sourceFileName": "../../../packages/pricing/src/models/price.ts",
			"qualifiedName": "default.amount"
		},
		"7813": {
			"sourceFileName": "../../../packages/pricing/src/models/price.ts",
			"qualifiedName": "default.min_quantity"
		},
		"7814": {
			"sourceFileName": "../../../packages/pricing/src/models/price.ts",
			"qualifiedName": "default.max_quantity"
		},
		"7815": {
			"sourceFileName": "../../../packages/pricing/src/models/price.ts",
			"qualifiedName": "default.price_set_id"
		},
		"7816": {
			"sourceFileName": "../../../packages/pricing/src/models/price.ts",
			"qualifiedName": "default.price_set"
		},
		"7817": {
			"sourceFileName": "../../../packages/pricing/src/models/price.ts",
			"qualifiedName": "default.rules_count"
		},
		"7818": {
			"sourceFileName": "../../../packages/pricing/src/models/price.ts",
			"qualifiedName": "default.price_rules"
		},
		"7819": {
			"sourceFileName": "../../../packages/pricing/src/models/price.ts",
			"qualifiedName": "default.price_list_id"
		},
		"7820": {
			"sourceFileName": "../../../packages/pricing/src/models/price.ts",
			"qualifiedName": "default.price_list"
		},
		"7821": {
			"sourceFileName": "../../../packages/pricing/src/models/price.ts",
			"qualifiedName": "default.created_at"
		},
		"7822": {
			"sourceFileName": "../../../packages/pricing/src/models/price.ts",
			"qualifiedName": "default.updated_at"
		},
		"7823": {
			"sourceFileName": "../../../packages/pricing/src/models/price.ts",
			"qualifiedName": "default.deleted_at"
		},
		"7824": {
			"sourceFileName": "../../../packages/pricing/src/models/price.ts",
			"qualifiedName": "default.onCreate"
		},
		"7825": {
			"sourceFileName": "../../../packages/pricing/src/models/price.ts",
			"qualifiedName": "default.onCreate"
		},
		"7826": {
			"sourceFileName": "../../../packages/pricing/src/models/price.ts",
			"qualifiedName": "default.onInit"
		},
		"7827": {
			"sourceFileName": "../../../packages/pricing/src/models/price.ts",
			"qualifiedName": "default.onInit"
		},
		"7828": {
			"sourceFileName": "../../../packages/pricing/src/models/price.ts",
			"qualifiedName": "default.[OptionalProps]"
		},
		"7829": {
			"sourceFileName": "../../../packages/pricing/src/models/price-list.ts",
			"qualifiedName": "default"
		},
		"7832": {
			"sourceFileName": "../../../packages/pricing/src/models/price-list.ts",
			"qualifiedName": "default.id"
		},
		"7833": {
			"sourceFileName": "../../../packages/pricing/src/models/price-list.ts",
			"qualifiedName": "default.title"
		},
		"7834": {
			"sourceFileName": "../../../packages/pricing/src/models/price-list.ts",
			"qualifiedName": "default.description"
		},
		"7835": {
			"sourceFileName": "../../../packages/pricing/src/models/price-list.ts",
			"qualifiedName": "default.status"
		},
		"7836": {
			"sourceFileName": "../../../packages/pricing/src/models/price-list.ts",
			"qualifiedName": "default.type"
		},
		"7837": {
			"sourceFileName": "../../../packages/pricing/src/models/price-list.ts",
			"qualifiedName": "default.starts_at"
		},
		"7838": {
			"sourceFileName": "../../../packages/pricing/src/models/price-list.ts",
			"qualifiedName": "default.ends_at"
		},
		"7839": {
			"sourceFileName": "../../../packages/pricing/src/models/price-list.ts",
			"qualifiedName": "default.prices"
		},
		"7840": {
			"sourceFileName": "../../../packages/pricing/src/models/price-list.ts",
			"qualifiedName": "default.price_list_rules"
		},
		"7841": {
			"sourceFileName": "../../../packages/pricing/src/models/price-list.ts",
			"qualifiedName": "default.rule_types"
		},
		"7842": {
			"sourceFileName": "../../../packages/pricing/src/models/price-list.ts",
			"qualifiedName": "default.rules_count"
		},
		"7843": {
			"sourceFileName": "../../../packages/pricing/src/models/price-list.ts",
			"qualifiedName": "default.created_at"
		},
		"7844": {
			"sourceFileName": "../../../packages/pricing/src/models/price-list.ts",
			"qualifiedName": "default.updated_at"
		},
		"7845": {
			"sourceFileName": "../../../packages/pricing/src/models/price-list.ts",
			"qualifiedName": "default.deleted_at"
		},
		"7846": {
			"sourceFileName": "../../../packages/pricing/src/models/price-list.ts",
			"qualifiedName": "default.onCreate"
		},
		"7847": {
			"sourceFileName": "../../../packages/pricing/src/models/price-list.ts",
			"qualifiedName": "default.onCreate"
		},
		"7848": {
			"sourceFileName": "../../../packages/pricing/src/models/price-list.ts",
			"qualifiedName": "default.onInit"
		},
		"7849": {
			"sourceFileName": "../../../packages/pricing/src/models/price-list.ts",
			"qualifiedName": "default.onInit"
		},
		"7850": {
			"sourceFileName": "../../../packages/pricing/src/models/price-list.ts",
			"qualifiedName": "default.[OptionalProps]"
		},
		"7851": {
			"sourceFileName": "../../../packages/pricing/src/models/price-list-rule.ts",
			"qualifiedName": "default"
		},
		"7854": {
			"sourceFileName": "../../../packages/pricing/src/models/price-list-rule.ts",
			"qualifiedName": "default.id"
		},
		"7855": {
			"sourceFileName": "../../../packages/pricing/src/models/price-list-rule.ts",
			"qualifiedName": "default.rule_type_id"
		},
		"7856": {
			"sourceFileName": "../../../packages/pricing/src/models/price-list-rule.ts",
			"qualifiedName": "default.rule_type"
		},
		"7857": {
			"sourceFileName": "../../../packages/pricing/src/models/price-list-rule.ts",
			"qualifiedName": "default.price_list_rule_values"
		},
		"7858": {
			"sourceFileName": "../../../packages/pricing/src/models/price-list-rule.ts",
			"qualifiedName": "default.price_list_id"
		},
		"7859": {
			"sourceFileName": "../../../packages/pricing/src/models/price-list-rule.ts",
			"qualifiedName": "default.price_list"
		},
		"7860": {
			"sourceFileName": "../../../packages/pricing/src/models/price-list-rule.ts",
			"qualifiedName": "default.created_at"
		},
		"7861": {
			"sourceFileName": "../../../packages/pricing/src/models/price-list-rule.ts",
			"qualifiedName": "default.updated_at"
		},
		"7862": {
			"sourceFileName": "../../../packages/pricing/src/models/price-list-rule.ts",
			"qualifiedName": "default.deleted_at"
		},
		"7863": {
			"sourceFileName": "../../../packages/pricing/src/models/price-list-rule.ts",
			"qualifiedName": "default.beforeCreate"
		},
		"7864": {
			"sourceFileName": "../../../packages/pricing/src/models/price-list-rule.ts",
			"qualifiedName": "default.beforeCreate"
		},
		"7865": {
			"sourceFileName": "../../../packages/pricing/src/models/price-list-rule.ts",
			"qualifiedName": "default.onInit"
		},
		"7866": {
			"sourceFileName": "../../../packages/pricing/src/models/price-list-rule.ts",
			"qualifiedName": "default.onInit"
		},
		"7867": {
			"sourceFileName": "../../../packages/pricing/src/models/price-list-rule.ts",
			"qualifiedName": "default.[OptionalProps]"
		},
		"7868": {
			"sourceFileName": "../../../packages/pricing/src/models/price-list-rule-value.ts",
			"qualifiedName": "default"
		},
		"7871": {
			"sourceFileName": "../../../packages/pricing/src/models/price-list-rule-value.ts",
			"qualifiedName": "default.id"
		},
		"7872": {
			"sourceFileName": "../../../packages/pricing/src/models/price-list-rule-value.ts",
			"qualifiedName": "default.price_list_rule_id"
		},
		"7873": {
			"sourceFileName": "../../../packages/pricing/src/models/price-list-rule-value.ts",
			"qualifiedName": "default.price_list_rule"
		},
		"7874": {
			"sourceFileName": "../../../packages/pricing/src/models/price-list-rule-value.ts",
			"qualifiedName": "default.value"
		},
		"7875": {
			"sourceFileName": "../../../packages/pricing/src/models/price-list-rule-value.ts",
			"qualifiedName": "default.created_at"
		},
		"7876": {
			"sourceFileName": "../../../packages/pricing/src/models/price-list-rule-value.ts",
			"qualifiedName": "default.updated_at"
		},
		"7877": {
			"sourceFileName": "../../../packages/pricing/src/models/price-list-rule-value.ts",
			"qualifiedName": "default.deleted_at"
		},
		"7878": {
			"sourceFileName": "../../../packages/pricing/src/models/price-list-rule-value.ts",
			"qualifiedName": "default.onCreate"
		},
		"7879": {
			"sourceFileName": "../../../packages/pricing/src/models/price-list-rule-value.ts",
			"qualifiedName": "default.onCreate"
		},
		"7880": {
			"sourceFileName": "../../../packages/pricing/src/models/price-list-rule-value.ts",
			"qualifiedName": "default.onInit"
		},
		"7881": {
			"sourceFileName": "../../../packages/pricing/src/models/price-list-rule-value.ts",
			"qualifiedName": "default.onInit"
		},
		"7882": {
			"sourceFileName": "../../../packages/pricing/src/models/price-list-rule-value.ts",
			"qualifiedName": "default.[OptionalProps]"
		},
		"7883": {
			"sourceFileName": "../../../packages/pricing/src/models/price-rule.ts",
			"qualifiedName": "default"
		},
		"7886": {
			"sourceFileName": "../../../packages/pricing/src/models/price-rule.ts",
			"qualifiedName": "default.id"
		},
		"7887": {
			"sourceFileName": "../../../packages/pricing/src/models/price-rule.ts",
			"qualifiedName": "default.price_set_id"
		},
		"7888": {
			"sourceFileName": "../../../packages/pricing/src/models/price-rule.ts",
			"qualifiedName": "default.price_set"
		},
		"7889": {
			"sourceFileName": "../../../packages/pricing/src/models/price-rule.ts",
			"qualifiedName": "default.rule_type_id"
		},
		"7890": {
			"sourceFileName": "../../../packages/pricing/src/models/price-rule.ts",
			"qualifiedName": "default.rule_type"
		},
		"7891": {
			"sourceFileName": "../../../packages/pricing/src/models/price-rule.ts",
			"qualifiedName": "default.value"
		},
		"7892": {
			"sourceFileName": "../../../packages/pricing/src/models/price-rule.ts",
			"qualifiedName": "default.priority"
		},
		"7893": {
			"sourceFileName": "../../../packages/pricing/src/models/price-rule.ts",
			"qualifiedName": "default.price_id"
		},
		"7894": {
			"sourceFileName": "../../../packages/pricing/src/models/price-rule.ts",
			"qualifiedName": "default.price"
		},
		"7895": {
			"sourceFileName": "../../../packages/pricing/src/models/price-rule.ts",
			"qualifiedName": "default.created_at"
		},
		"7896": {
			"sourceFileName": "../../../packages/pricing/src/models/price-rule.ts",
			"qualifiedName": "default.updated_at"
		},
		"7897": {
			"sourceFileName": "../../../packages/pricing/src/models/price-rule.ts",
			"qualifiedName": "default.deleted_at"
		},
		"7898": {
			"sourceFileName": "../../../packages/pricing/src/models/price-rule.ts",
			"qualifiedName": "default.beforeCreate"
		},
		"7899": {
			"sourceFileName": "../../../packages/pricing/src/models/price-rule.ts",
			"qualifiedName": "default.beforeCreate"
		},
		"7900": {
			"sourceFileName": "../../../packages/pricing/src/models/price-rule.ts",
			"qualifiedName": "default.onInit"
		},
		"7901": {
			"sourceFileName": "../../../packages/pricing/src/models/price-rule.ts",
			"qualifiedName": "default.onInit"
		},
		"7902": {
			"sourceFileName": "../../../packages/pricing/src/models/price-rule.ts",
			"qualifiedName": "default.[OptionalProps]"
		},
		"7903": {
			"sourceFileName": "../../../packages/pricing/src/models/price-set.ts",
			"qualifiedName": "default"
		},
		"7906": {
			"sourceFileName": "../../../packages/pricing/src/models/price-set.ts",
			"qualifiedName": "default.id"
		},
		"7907": {
			"sourceFileName": "../../../packages/pricing/src/models/price-set.ts",
			"qualifiedName": "default.prices"
		},
		"7908": {
			"sourceFileName": "../../../packages/pricing/src/models/price-set.ts",
			"qualifiedName": "default.price_rules"
		},
		"7909": {
			"sourceFileName": "../../../packages/pricing/src/models/price-set.ts",
			"qualifiedName": "default.rule_types"
		},
		"7910": {
			"sourceFileName": "../../../packages/pricing/src/models/price-set.ts",
			"qualifiedName": "default.created_at"
		},
		"7911": {
			"sourceFileName": "../../../packages/pricing/src/models/price-set.ts",
			"qualifiedName": "default.updated_at"
		},
		"7912": {
			"sourceFileName": "../../../packages/pricing/src/models/price-set.ts",
			"qualifiedName": "default.deleted_at"
		},
		"7913": {
			"sourceFileName": "../../../packages/pricing/src/models/price-set.ts",
			"qualifiedName": "default.onCreate"
		},
		"7914": {
			"sourceFileName": "../../../packages/pricing/src/models/price-set.ts",
			"qualifiedName": "default.onCreate"
		},
		"7915": {
			"sourceFileName": "../../../packages/pricing/src/models/price-set.ts",
			"qualifiedName": "default.onInit"
		},
		"7916": {
			"sourceFileName": "../../../packages/pricing/src/models/price-set.ts",
			"qualifiedName": "default.onInit"
		},
		"7917": {
			"sourceFileName": "../../../packages/pricing/src/models/price-set-rule-type.ts",
			"qualifiedName": "default"
		},
		"7920": {
			"sourceFileName": "../../../packages/pricing/src/models/price-set-rule-type.ts",
			"qualifiedName": "default.id"
		},
		"7921": {
			"sourceFileName": "../../../packages/pricing/src/models/price-set-rule-type.ts",
			"qualifiedName": "default.price_set_id"
		},
		"7922": {
			"sourceFileName": "../../../packages/pricing/src/models/price-set-rule-type.ts",
			"qualifiedName": "default.rule_type_id"
		},
		"7923": {
			"sourceFileName": "../../../packages/pricing/src/models/price-set-rule-type.ts",
			"qualifiedName": "default.created_at"
		},
		"7924": {
			"sourceFileName": "../../../packages/pricing/src/models/price-set-rule-type.ts",
			"qualifiedName": "default.updated_at"
		},
		"7925": {
			"sourceFileName": "../../../packages/pricing/src/models/price-set-rule-type.ts",
			"qualifiedName": "default.deleted_at"
		},
		"7926": {
			"sourceFileName": "../../../packages/pricing/src/models/price-set-rule-type.ts",
			"qualifiedName": "default.onCreate"
		},
		"7927": {
			"sourceFileName": "../../../packages/pricing/src/models/price-set-rule-type.ts",
			"qualifiedName": "default.onCreate"
		},
		"7928": {
			"sourceFileName": "../../../packages/pricing/src/models/price-set-rule-type.ts",
			"qualifiedName": "default.onInit"
		},
		"7929": {
			"sourceFileName": "../../../packages/pricing/src/models/price-set-rule-type.ts",
			"qualifiedName": "default.onInit"
		},
		"7930": {
			"sourceFileName": "../../../packages/pricing/src/models/rule-type.ts",
			"qualifiedName": "RuleType"
		},
		"7933": {
			"sourceFileName": "../../../packages/pricing/src/models/rule-type.ts",
			"qualifiedName": "RuleType.id"
		},
		"7934": {
			"sourceFileName": "../../../packages/pricing/src/models/rule-type.ts",
			"qualifiedName": "RuleType.name"
		},
		"7935": {
			"sourceFileName": "../../../packages/pricing/src/models/rule-type.ts",
			"qualifiedName": "RuleType.rule_attribute"
		},
		"7936": {
			"sourceFileName": "../../../packages/pricing/src/models/rule-type.ts",
			"qualifiedName": "RuleType.default_priority"
		},
		"7937": {
			"sourceFileName": "../../../packages/pricing/src/models/rule-type.ts",
			"qualifiedName": "RuleType.price_sets"
		},
		"7938": {
			"sourceFileName": "../../../packages/pricing/src/models/rule-type.ts",
			"qualifiedName": "RuleType.created_at"
		},
		"7939": {
			"sourceFileName": "../../../packages/pricing/src/models/rule-type.ts",
			"qualifiedName": "RuleType.updated_at"
		},
		"7940": {
			"sourceFileName": "../../../packages/pricing/src/models/rule-type.ts",
			"qualifiedName": "RuleType.deleted_at"
		},
		"7941": {
			"sourceFileName": "../../../packages/pricing/src/models/rule-type.ts",
			"qualifiedName": "RuleType.onCreate"
		},
		"7942": {
			"sourceFileName": "../../../packages/pricing/src/models/rule-type.ts",
			"qualifiedName": "RuleType.onCreate"
		},
		"7943": {
			"sourceFileName": "../../../packages/pricing/src/models/rule-type.ts",
			"qualifiedName": "RuleType.onInit"
		},
		"7944": {
			"sourceFileName": "../../../packages/pricing/src/models/rule-type.ts",
			"qualifiedName": "RuleType.onInit"
		},
		"7945": {
			"sourceFileName": "../../../packages/pricing/src/models/rule-type.ts",
			"qualifiedName": "RuleType.[OptionalProps]"
		}
	}
}