{
	"id": 9649,
	"name": "pricing-models",
	"variant": "project",
	"kind": 1,
	"flags": {},
	"comment": {
		"summary": [
			{
				"text": "## Relations Overview\n\n",
				"kind": "text"
			},
			{
				"text": "```mermaid\nerDiagram\n\tPrice }|--|{ PriceSet : price_set\n\tPrice ||--|| PriceRule : price_rules\n\tPrice }|--|{ PriceList : price_list\n\tPriceList ||--|| PriceListRule : price_list_rules\n\n```",
				"kind": "code"
			}
		]
	},
	"children": [
		{
			"id": 9695,
			"name": "PriceListRule",
			"variant": "declaration",
			"kind": 128,
			"flags": {},
			"children": [
				{
					"id": 9696,
					"name": "constructor",
					"variant": "declaration",
					"kind": 512,
					"flags": {},
					"signatures": [
						{
							"id": 9697,
							"name": "new PriceListRule",
							"variant": "signature",
							"kind": 16384,
							"flags": {},
							"type": {
								"type": "reference",
								"target": 9695,
								"name": "PriceListRule",
								"package": "@medusajs/pricing",
								"qualifiedName": "default"
							}
						}
					]
				},
				{
					"id": 9710,
					"name": "[OptionalProps]",
					"variant": "declaration",
					"kind": 1024,
					"flags": {},
					"type": {
						"type": "reference",
						"target": {
							"sourceFileName": "../../../../packages/core/types/src/dal/entity.ts",
							"qualifiedName": "SoftDeletableModelDateColumns"
						},
						"name": "SoftDeletableModelDateColumns",
						"package": "@medusajs/types"
					}
				},
				{
					"id": 9698,
					"name": "id",
					"variant": "declaration",
					"kind": 1024,
					"flags": {},
					"type": {
						"type": "intrinsic",
						"name": "string"
					}
				},
				{
					"id": 9699,
					"name": "attribute",
					"variant": "declaration",
					"kind": 1024,
					"flags": {},
					"type": {
						"type": "intrinsic",
						"name": "string"
					}
				},
				{
					"id": 9700,
					"name": "value",
					"variant": "declaration",
					"kind": 1024,
					"flags": {},
					"type": {
						"type": "union",
						"types": [
							{
								"type": "literal",
								"value": null
							},
							{
								"type": "intrinsic",
								"name": "string"
							},
							{
								"type": "array",
								"elementType": {
									"type": "intrinsic",
									"name": "string"
								}
							}
						]
					},
					"defaultValue": "null"
				},
				{
					"id": 9701,
					"name": "price_list_id",
					"variant": "declaration",
					"kind": 1024,
					"flags": {},
					"type": {
						"type": "intrinsic",
						"name": "string"
					}
				},
				{
					"id": 9702,
					"name": "price_list",
					"variant": "declaration",
					"kind": 1024,
					"flags": {},
					"type": {
						"type": "reference",
						"target": 9674,
						"name": "PriceList",
						"package": "@medusajs/pricing",
						"qualifiedName": "default"
					}
				},
				{
					"id": 9703,
					"name": "created_at",
					"variant": "declaration",
					"kind": 1024,
					"flags": {},
					"type": {
						"type": "reference",
						"target": {
							"sourceFileName": "../../node_modules/typescript/lib/lib.es5.d.ts",
							"qualifiedName": "Date"
						},
						"name": "Date",
						"package": "typescript"
					}
				},
				{
					"id": 9704,
					"name": "updated_at",
					"variant": "declaration",
					"kind": 1024,
					"flags": {},
					"type": {
						"type": "reference",
						"target": {
							"sourceFileName": "../../node_modules/typescript/lib/lib.es5.d.ts",
							"qualifiedName": "Date"
						},
						"name": "Date",
						"package": "typescript"
					}
				},
				{
					"id": 9705,
					"name": "deleted_at",
					"variant": "declaration",
					"kind": 1024,
					"flags": {},
					"type": {
						"type": "union",
						"types": [
							{
								"type": "literal",
								"value": null
							},
							{
								"type": "reference",
								"target": {
									"sourceFileName": "../../node_modules/typescript/lib/lib.es5.d.ts",
									"qualifiedName": "Date"
								},
								"name": "Date",
								"package": "typescript"
							}
						]
					},
					"defaultValue": "null"
				},
				{
					"id": 9706,
					"name": "beforeCreate",
					"variant": "declaration",
					"kind": 2048,
					"flags": {},
					"signatures": [
						{
							"id": 9707,
							"name": "beforeCreate",
							"variant": "signature",
							"kind": 4096,
							"flags": {},
							"type": {
								"type": "intrinsic",
								"name": "void"
							}
						}
					]
				},
				{
					"id": 9708,
					"name": "onInit",
					"variant": "declaration",
					"kind": 2048,
					"flags": {},
					"signatures": [
						{
							"id": 9709,
							"name": "onInit",
							"variant": "signature",
							"kind": 4096,
							"flags": {},
							"type": {
								"type": "intrinsic",
								"name": "void"
							}
						}
					]
				}
			],
			"groups": [
				{
					"title": "Constructors",
					"children": [
						9696
					]
				},
				{
					"title": "Properties",
					"children": [
						9710,
						9698,
						9699,
						9700,
						9701,
						9702,
						9703,
						9704,
						9705
					]
				},
				{
					"title": "Methods",
					"children": [
						9706,
						9708
					]
				}
			]
		},
		{
			"id": 9674,
			"name": "PriceList",
			"variant": "declaration",
			"kind": 128,
			"flags": {},
			"children": [
				{
					"id": 9675,
					"name": "constructor",
					"variant": "declaration",
					"kind": 512,
					"flags": {},
					"signatures": [
						{
							"id": 9676,
							"name": "new PriceList",
							"variant": "signature",
							"kind": 16384,
							"flags": {},
							"type": {
								"type": "reference",
								"target": 9674,
								"name": "PriceList",
								"package": "@medusajs/pricing",
								"qualifiedName": "default"
							}
						}
					]
				},
				{
					"id": 9694,
					"name": "[OptionalProps]",
					"variant": "declaration",
					"kind": 1024,
					"flags": {},
					"type": {
						"type": "reference",
						"target": {
							"sourceFileName": "../../../../packages/modules/pricing/src/models/price-list.ts",
							"qualifiedName": "OptionalFields"
						},
						"name": "OptionalFields",
						"package": "@medusajs/pricing"
					}
				},
				{
					"id": 9677,
					"name": "id",
					"variant": "declaration",
					"kind": 1024,
					"flags": {},
					"type": {
						"type": "intrinsic",
						"name": "string"
					}
				},
				{
					"id": 9678,
					"name": "title",
					"variant": "declaration",
					"kind": 1024,
					"flags": {},
					"type": {
						"type": "intrinsic",
						"name": "string"
					}
				},
				{
					"id": 9679,
					"name": "description",
					"variant": "declaration",
					"kind": 1024,
					"flags": {},
					"type": {
						"type": "intrinsic",
						"name": "string"
					}
				},
				{
					"id": 9680,
					"name": "status",
					"variant": "declaration",
					"kind": 1024,
					"flags": {},
					"type": {
						"type": "reference",
						"target": {
							"sourceFileName": "../../../../packages/core/utils/src/pricing/price-list.ts",
							"qualifiedName": "PriceListStatus"
						},
						"name": "PriceListStatus",
						"package": "@medusajs/utils"
					}
				},
				{
					"id": 9681,
					"name": "type",
					"variant": "declaration",
					"kind": 1024,
					"flags": {},
					"type": {
						"type": "reference",
						"target": {
							"sourceFileName": "../../../../packages/core/utils/src/pricing/price-list.ts",
							"qualifiedName": "PriceListType"
						},
						"name": "PriceListType",
						"package": "@medusajs/utils"
					}
				},
				{
					"id": 9682,
					"name": "starts_at",
					"variant": "declaration",
					"kind": 1024,
					"flags": {},
					"type": {
						"type": "union",
						"types": [
							{
								"type": "literal",
								"value": null
							},
							{
								"type": "reference",
								"target": {
									"sourceFileName": "../../node_modules/typescript/lib/lib.es5.d.ts",
									"qualifiedName": "Date"
								},
								"name": "Date",
								"package": "typescript"
							}
						]
					},
					"defaultValue": "null"
				},
				{
					"id": 9683,
					"name": "ends_at",
					"variant": "declaration",
					"kind": 1024,
					"flags": {},
					"type": {
						"type": "union",
						"types": [
							{
								"type": "literal",
								"value": null
							},
							{
								"type": "reference",
								"target": {
									"sourceFileName": "../../node_modules/typescript/lib/lib.es5.d.ts",
									"qualifiedName": "Date"
								},
								"name": "Date",
								"package": "typescript"
							}
						]
					},
					"defaultValue": "null"
				},
				{
					"id": 9684,
					"name": "prices",
					"variant": "declaration",
					"kind": 1024,
					"flags": {},
					"type": {
						"type": "reference",
						"target": {
							"sourceFileName": "../../../../node_modules/@mikro-orm/core/entity/Collection.d.ts",
							"qualifiedName": "Collection"
						},
						"typeArguments": [
							{
								"type": "reference",
								"target": 9650,
								"name": "Price",
								"package": "@medusajs/pricing",
								"qualifiedName": "default"
							},
							{
								"type": "intrinsic",
								"name": "object"
							}
						],
						"name": "Collection",
						"package": "@mikro-orm/core"
					},
					"defaultValue": "..."
				},
				{
					"id": 9685,
					"name": "price_list_rules",
					"variant": "declaration",
					"kind": 1024,
					"flags": {},
					"type": {
						"type": "reference",
						"target": {
							"sourceFileName": "../../../../node_modules/@mikro-orm/core/entity/Collection.d.ts",
							"qualifiedName": "Collection"
						},
						"typeArguments": [
							{
								"type": "reference",
								"target": 9695,
								"name": "PriceListRule",
								"package": "@medusajs/pricing",
								"qualifiedName": "default"
							},
							{
								"type": "intrinsic",
								"name": "object"
							}
						],
						"name": "Collection",
						"package": "@mikro-orm/core"
					},
					"defaultValue": "..."
				},
				{
					"id": 9686,
					"name": "rules_count",
					"variant": "declaration",
					"kind": 1024,
					"flags": {},
					"type": {
						"type": "intrinsic",
						"name": "number"
					},
					"defaultValue": "0"
				},
				{
					"id": 9687,
					"name": "created_at",
					"variant": "declaration",
					"kind": 1024,
					"flags": {},
					"type": {
						"type": "reference",
						"target": {
							"sourceFileName": "../../node_modules/typescript/lib/lib.es5.d.ts",
							"qualifiedName": "Date"
						},
						"name": "Date",
						"package": "typescript"
					}
				},
				{
					"id": 9688,
					"name": "updated_at",
					"variant": "declaration",
					"kind": 1024,
					"flags": {},
					"type": {
						"type": "reference",
						"target": {
							"sourceFileName": "../../node_modules/typescript/lib/lib.es5.d.ts",
							"qualifiedName": "Date"
						},
						"name": "Date",
						"package": "typescript"
					}
				},
				{
					"id": 9689,
					"name": "deleted_at",
					"variant": "declaration",
					"kind": 1024,
					"flags": {},
					"type": {
						"type": "union",
						"types": [
							{
								"type": "literal",
								"value": null
							},
							{
								"type": "reference",
								"target": {
									"sourceFileName": "../../node_modules/typescript/lib/lib.es5.d.ts",
									"qualifiedName": "Date"
								},
								"name": "Date",
								"package": "typescript"
							}
						]
					},
					"defaultValue": "null"
				},
				{
					"id": 9690,
					"name": "onCreate",
					"variant": "declaration",
					"kind": 2048,
					"flags": {},
					"signatures": [
						{
							"id": 9691,
							"name": "onCreate",
							"variant": "signature",
							"kind": 4096,
							"flags": {},
							"type": {
								"type": "intrinsic",
								"name": "void"
							}
						}
					]
				},
				{
					"id": 9692,
					"name": "onInit",
					"variant": "declaration",
					"kind": 2048,
					"flags": {},
					"signatures": [
						{
							"id": 9693,
							"name": "onInit",
							"variant": "signature",
							"kind": 4096,
							"flags": {},
							"type": {
								"type": "intrinsic",
								"name": "void"
							}
						}
					]
				}
			],
			"groups": [
				{
					"title": "Constructors",
					"children": [
						9675
					]
				},
				{
					"title": "Properties",
					"children": [
						9694,
						9677,
						9678,
						9679,
						9680,
						9681,
						9682,
						9683,
						9684,
						9685,
						9686,
						9687,
						9688,
						9689
					]
				},
				{
					"title": "Methods",
					"children": [
						9690,
						9692
					]
				}
			]
		},
		{
			"id": 9740,
			"name": "PricePreference",
			"variant": "declaration",
			"kind": 128,
			"flags": {},
			"children": [
				{
					"id": 9741,
					"name": "constructor",
					"variant": "declaration",
					"kind": 512,
					"flags": {},
					"signatures": [
						{
							"id": 9742,
							"name": "new PricePreference",
							"variant": "signature",
							"kind": 16384,
							"flags": {},
							"type": {
								"type": "reference",
								"target": 9740,
								"name": "PricePreference",
								"package": "@medusajs/pricing",
								"qualifiedName": "default"
							}
						}
					]
				},
				{
					"id": 9743,
					"name": "id",
					"variant": "declaration",
					"kind": 1024,
					"flags": {},
					"type": {
						"type": "intrinsic",
						"name": "string"
					}
				},
				{
					"id": 9744,
					"name": "attribute",
					"variant": "declaration",
					"kind": 1024,
					"flags": {},
					"type": {
						"type": "intrinsic",
						"name": "string"
					}
				},
				{
					"id": 9745,
					"name": "value",
					"variant": "declaration",
					"kind": 1024,
					"flags": {},
					"type": {
						"type": "union",
						"types": [
							{
								"type": "literal",
								"value": null
							},
							{
								"type": "intrinsic",
								"name": "string"
							}
						]
					},
					"defaultValue": "null"
				},
				{
					"id": 9746,
					"name": "is_tax_inclusive",
					"variant": "declaration",
					"kind": 1024,
					"flags": {},
					"type": {
						"type": "intrinsic",
						"name": "boolean"
					}
				},
				{
					"id": 9747,
					"name": "created_at",
					"variant": "declaration",
					"kind": 1024,
					"flags": {},
					"type": {
						"type": "reference",
						"target": {
							"sourceFileName": "../../node_modules/typescript/lib/lib.es5.d.ts",
							"qualifiedName": "Date"
						},
						"name": "Date",
						"package": "typescript"
					}
				},
				{
					"id": 9748,
					"name": "updated_at",
					"variant": "declaration",
					"kind": 1024,
					"flags": {},
					"type": {
						"type": "reference",
						"target": {
							"sourceFileName": "../../node_modules/typescript/lib/lib.es5.d.ts",
							"qualifiedName": "Date"
						},
						"name": "Date",
						"package": "typescript"
					}
				},
				{
					"id": 9749,
					"name": "deleted_at",
					"variant": "declaration",
					"kind": 1024,
					"flags": {},
					"type": {
						"type": "union",
						"types": [
							{
								"type": "literal",
								"value": null
							},
							{
								"type": "reference",
								"target": {
									"sourceFileName": "../../node_modules/typescript/lib/lib.es5.d.ts",
									"qualifiedName": "Date"
								},
								"name": "Date",
								"package": "typescript"
							}
						]
					},
					"defaultValue": "null"
				},
				{
					"id": 9750,
					"name": "onCreate",
					"variant": "declaration",
					"kind": 2048,
					"flags": {},
					"signatures": [
						{
							"id": 9751,
							"name": "onCreate",
							"variant": "signature",
							"kind": 4096,
							"flags": {},
							"type": {
								"type": "intrinsic",
								"name": "void"
							}
						}
					]
				},
				{
					"id": 9752,
					"name": "onInit",
					"variant": "declaration",
					"kind": 2048,
					"flags": {},
					"signatures": [
						{
							"id": 9753,
							"name": "onInit",
							"variant": "signature",
							"kind": 4096,
							"flags": {},
							"type": {
								"type": "intrinsic",
								"name": "void"
							}
						}
					]
				}
			],
			"groups": [
				{
					"title": "Constructors",
					"children": [
						9741
					]
				},
				{
					"title": "Properties",
					"children": [
						9743,
						9744,
						9745,
						9746,
						9747,
						9748,
						9749
					]
				},
				{
					"title": "Methods",
					"children": [
						9750,
						9752
					]
				}
			]
		},
		{
			"id": 9711,
			"name": "PriceRule",
			"variant": "declaration",
			"kind": 128,
			"flags": {},
			"children": [
				{
					"id": 9712,
					"name": "constructor",
					"variant": "declaration",
					"kind": 512,
					"flags": {},
					"signatures": [
						{
							"id": 9713,
							"name": "new PriceRule",
							"variant": "signature",
							"kind": 16384,
							"flags": {},
							"type": {
								"type": "reference",
								"target": 9711,
								"name": "PriceRule",
								"package": "@medusajs/pricing",
								"qualifiedName": "default"
							}
						}
					]
				},
				{
					"id": 9727,
					"name": "[OptionalProps]",
					"variant": "declaration",
					"kind": 1024,
					"flags": {
						"isOptional": true
					},
					"type": {
						"type": "reference",
						"target": {
							"sourceFileName": "../../../../packages/core/types/src/dal/entity.ts",
							"qualifiedName": "SoftDeletableModelDateColumns"
						},
						"name": "SoftDeletableModelDateColumns",
						"package": "@medusajs/types"
					}
				},
				{
					"id": 9714,
					"name": "id",
					"variant": "declaration",
					"kind": 1024,
					"flags": {},
					"type": {
						"type": "intrinsic",
						"name": "string"
					}
				},
				{
					"id": 9715,
					"name": "attribute",
					"variant": "declaration",
					"kind": 1024,
					"flags": {},
					"type": {
						"type": "intrinsic",
						"name": "string"
					}
				},
				{
					"id": 9716,
					"name": "value",
					"variant": "declaration",
					"kind": 1024,
					"flags": {},
					"type": {
						"type": "intrinsic",
						"name": "string"
					}
				},
				{
					"id": 9717,
					"name": "priority",
					"variant": "declaration",
					"kind": 1024,
					"flags": {},
					"type": {
						"type": "intrinsic",
						"name": "number"
					},
					"defaultValue": "0"
				},
				{
					"id": 9718,
					"name": "price_id",
					"variant": "declaration",
					"kind": 1024,
					"flags": {},
					"type": {
						"type": "intrinsic",
						"name": "string"
					}
				},
				{
					"id": 9719,
					"name": "price",
					"variant": "declaration",
					"kind": 1024,
					"flags": {},
					"type": {
						"type": "reference",
						"target": 9650,
						"name": "Price",
						"package": "@medusajs/pricing",
						"qualifiedName": "default"
					}
				},
				{
					"id": 9720,
					"name": "created_at",
					"variant": "declaration",
					"kind": 1024,
					"flags": {},
					"type": {
						"type": "reference",
						"target": {
							"sourceFileName": "../../node_modules/typescript/lib/lib.es5.d.ts",
							"qualifiedName": "Date"
						},
						"name": "Date",
						"package": "typescript"
					}
				},
				{
					"id": 9721,
					"name": "updated_at",
					"variant": "declaration",
					"kind": 1024,
					"flags": {},
					"type": {
						"type": "reference",
						"target": {
							"sourceFileName": "../../node_modules/typescript/lib/lib.es5.d.ts",
							"qualifiedName": "Date"
						},
						"name": "Date",
						"package": "typescript"
					}
				},
				{
					"id": 9722,
					"name": "deleted_at",
					"variant": "declaration",
					"kind": 1024,
					"flags": {},
					"type": {
						"type": "union",
						"types": [
							{
								"type": "literal",
								"value": null
							},
							{
								"type": "reference",
								"target": {
									"sourceFileName": "../../node_modules/typescript/lib/lib.es5.d.ts",
									"qualifiedName": "Date"
								},
								"name": "Date",
								"package": "typescript"
							}
						]
					},
					"defaultValue": "null"
				},
				{
					"id": 9723,
					"name": "beforeCreate",
					"variant": "declaration",
					"kind": 2048,
					"flags": {},
					"signatures": [
						{
							"id": 9724,
							"name": "beforeCreate",
							"variant": "signature",
							"kind": 4096,
							"flags": {},
							"type": {
								"type": "intrinsic",
								"name": "void"
							}
						}
					]
				},
				{
					"id": 9725,
					"name": "onInit",
					"variant": "declaration",
					"kind": 2048,
					"flags": {},
					"signatures": [
						{
							"id": 9726,
							"name": "onInit",
							"variant": "signature",
							"kind": 4096,
							"flags": {},
							"type": {
								"type": "intrinsic",
								"name": "void"
							}
						}
					]
				}
			],
			"groups": [
				{
					"title": "Constructors",
					"children": [
						9712
					]
				},
				{
					"title": "Properties",
					"children": [
						9727,
						9714,
						9715,
						9716,
						9717,
						9718,
						9719,
						9720,
						9721,
						9722
					]
				},
				{
					"title": "Methods",
					"children": [
						9723,
						9725
					]
				}
			]
		},
		{
			"id": 9728,
			"name": "PriceSet",
			"variant": "declaration",
			"kind": 128,
			"flags": {},
			"children": [
				{
					"id": 9729,
					"name": "constructor",
					"variant": "declaration",
					"kind": 512,
					"flags": {},
					"signatures": [
						{
							"id": 9730,
							"name": "new PriceSet",
							"variant": "signature",
							"kind": 16384,
							"flags": {},
							"type": {
								"type": "reference",
								"target": 9728,
								"name": "PriceSet",
								"package": "@medusajs/pricing",
								"qualifiedName": "default"
							}
						}
					]
				},
				{
					"id": 9731,
					"name": "id",
					"variant": "declaration",
					"kind": 1024,
					"flags": {},
					"type": {
						"type": "intrinsic",
						"name": "string"
					}
				},
				{
					"id": 9732,
					"name": "prices",
					"variant": "declaration",
					"kind": 1024,
					"flags": {},
					"type": {
						"type": "reference",
						"target": {
							"sourceFileName": "../../../../node_modules/@mikro-orm/core/entity/Collection.d.ts",
							"qualifiedName": "Collection"
						},
						"typeArguments": [
							{
								"type": "reference",
								"target": 9650,
								"name": "Price",
								"package": "@medusajs/pricing",
								"qualifiedName": "default"
							},
							{
								"type": "intrinsic",
								"name": "object"
							}
						],
						"name": "Collection",
						"package": "@mikro-orm/core"
					},
					"defaultValue": "..."
				},
				{
					"id": 9733,
					"name": "created_at",
					"variant": "declaration",
					"kind": 1024,
					"flags": {},
					"type": {
						"type": "reference",
						"target": {
							"sourceFileName": "../../node_modules/typescript/lib/lib.es5.d.ts",
							"qualifiedName": "Date"
						},
						"name": "Date",
						"package": "typescript"
					}
				},
				{
					"id": 9734,
					"name": "updated_at",
					"variant": "declaration",
					"kind": 1024,
					"flags": {},
					"type": {
						"type": "reference",
						"target": {
							"sourceFileName": "../../node_modules/typescript/lib/lib.es5.d.ts",
							"qualifiedName": "Date"
						},
						"name": "Date",
						"package": "typescript"
					}
				},
				{
					"id": 9735,
					"name": "deleted_at",
					"variant": "declaration",
					"kind": 1024,
					"flags": {},
					"type": {
						"type": "union",
						"types": [
							{
								"type": "literal",
								"value": null
							},
							{
								"type": "reference",
								"target": {
									"sourceFileName": "../../node_modules/typescript/lib/lib.es5.d.ts",
									"qualifiedName": "Date"
								},
								"name": "Date",
								"package": "typescript"
							}
						]
					},
					"defaultValue": "null"
				},
				{
					"id": 9736,
					"name": "onCreate",
					"variant": "declaration",
					"kind": 2048,
					"flags": {},
					"signatures": [
						{
							"id": 9737,
							"name": "onCreate",
							"variant": "signature",
							"kind": 4096,
							"flags": {},
							"type": {
								"type": "intrinsic",
								"name": "void"
							}
						}
					]
				},
				{
					"id": 9738,
					"name": "onInit",
					"variant": "declaration",
					"kind": 2048,
					"flags": {},
					"signatures": [
						{
							"id": 9739,
							"name": "onInit",
							"variant": "signature",
							"kind": 4096,
							"flags": {},
							"type": {
								"type": "intrinsic",
								"name": "void"
							}
						}
					]
				}
			],
			"groups": [
				{
					"title": "Constructors",
					"children": [
						9729
					]
				},
				{
					"title": "Properties",
					"children": [
						9731,
						9732,
						9733,
						9734,
						9735
					]
				},
				{
					"title": "Methods",
					"children": [
						9736,
						9738
					]
				}
			]
		},
		{
			"id": 9650,
			"name": "Price",
			"variant": "declaration",
			"kind": 128,
			"flags": {},
			"children": [
				{
					"id": 9651,
					"name": "constructor",
					"variant": "declaration",
					"kind": 512,
					"flags": {},
					"signatures": [
						{
							"id": 9652,
							"name": "new Price",
							"variant": "signature",
							"kind": 16384,
							"flags": {},
							"type": {
								"type": "reference",
								"target": 9650,
								"name": "Price",
								"package": "@medusajs/pricing",
								"qualifiedName": "default"
							}
						}
					]
				},
				{
					"id": 9673,
					"name": "[OptionalProps]",
					"variant": "declaration",
					"kind": 1024,
					"flags": {
						"isOptional": true
					},
					"type": {
						"type": "reference",
						"target": {
							"sourceFileName": "../../../../packages/core/types/src/dal/entity.ts",
							"qualifiedName": "SoftDeletableModelDateColumns"
						},
						"name": "SoftDeletableModelDateColumns",
						"package": "@medusajs/types"
					}
				},
				{
					"id": 9653,
					"name": "id",
					"variant": "declaration",
					"kind": 1024,
					"flags": {},
					"type": {
						"type": "intrinsic",
						"name": "string"
					}
				},
				{
					"id": 9654,
					"name": "title",
					"variant": "declaration",
					"kind": 1024,
					"flags": {},
					"type": {
						"type": "union",
						"types": [
							{
								"type": "literal",
								"value": null
							},
							{
								"type": "intrinsic",
								"name": "string"
							}
						]
					},
					"defaultValue": "null"
				},
				{
					"id": 9655,
					"name": "currency_code",
					"variant": "declaration",
					"kind": 1024,
					"flags": {},
					"type": {
						"type": "intrinsic",
						"name": "string"
					}
				},
				{
					"id": 9656,
					"name": "amount",
					"variant": "declaration",
					"kind": 1024,
					"flags": {},
					"type": {
						"type": "union",
						"types": [
							{
								"type": "intrinsic",
								"name": "number"
							},
							{
								"type": "reference",
								"target": {
									"sourceFileName": "../../../../packages/core/utils/src/totals/big-number.ts",
									"qualifiedName": "BigNumber"
								},
								"name": "BigNumber",
								"package": "@medusajs/utils"
							}
						]
					}
				},
				{
					"id": 9657,
					"name": "raw_amount",
					"variant": "declaration",
					"kind": 1024,
					"flags": {},
					"type": {
						"type": "reference",
						"target": {
							"sourceFileName": "../../node_modules/typescript/lib/lib.es5.d.ts",
							"qualifiedName": "Record"
						},
						"typeArguments": [
							{
								"type": "intrinsic",
								"name": "string"
							},
							{
								"type": "intrinsic",
								"name": "unknown"
							}
						],
						"name": "Record",
						"package": "typescript"
					}
				},
				{
					"id": 9658,
					"name": "min_quantity",
					"variant": "declaration",
					"kind": 1024,
					"flags": {},
					"type": {
						"type": "union",
						"types": [
							{
								"type": "literal",
								"value": null
							},
							{
								"type": "intrinsic",
								"name": "number"
							}
						]
					},
					"defaultValue": "null"
				},
				{
					"id": 9659,
					"name": "max_quantity",
					"variant": "declaration",
					"kind": 1024,
					"flags": {},
					"type": {
						"type": "union",
						"types": [
							{
								"type": "literal",
								"value": null
							},
							{
								"type": "intrinsic",
								"name": "number"
							}
						]
					},
					"defaultValue": "null"
				},
				{
					"id": 9660,
					"name": "price_set_id",
					"variant": "declaration",
					"kind": 1024,
					"flags": {},
					"type": {
						"type": "intrinsic",
						"name": "string"
					}
				},
				{
					"id": 9661,
					"name": "price_set",
					"variant": "declaration",
					"kind": 1024,
					"flags": {
						"isOptional": true
					},
					"type": {
						"type": "reference",
						"target": 9728,
						"name": "PriceSet",
						"package": "@medusajs/pricing",
						"qualifiedName": "default"
					}
				},
				{
					"id": 9662,
					"name": "rules_count",
					"variant": "declaration",
					"kind": 1024,
					"flags": {},
					"type": {
						"type": "intrinsic",
						"name": "number"
					},
					"defaultValue": "0"
				},
				{
					"id": 9663,
					"name": "price_rules",
					"variant": "declaration",
					"kind": 1024,
					"flags": {},
					"type": {
						"type": "reference",
						"target": {
							"sourceFileName": "../../../../node_modules/@mikro-orm/core/entity/Collection.d.ts",
							"qualifiedName": "Collection"
						},
						"typeArguments": [
							{
								"type": "reference",
								"target": 9711,
								"name": "PriceRule",
								"package": "@medusajs/pricing",
								"qualifiedName": "default"
							},
							{
								"type": "intrinsic",
								"name": "object"
							}
						],
						"name": "Collection",
						"package": "@mikro-orm/core"
					},
					"defaultValue": "..."
				},
				{
					"id": 9664,
					"name": "price_list_id",
					"variant": "declaration",
					"kind": 1024,
					"flags": {},
					"type": {
						"type": "union",
						"types": [
							{
								"type": "literal",
								"value": null
							},
							{
								"type": "intrinsic",
								"name": "string"
							}
						]
					},
					"defaultValue": "null"
				},
				{
					"id": 9665,
					"name": "price_list",
					"variant": "declaration",
					"kind": 1024,
					"flags": {},
					"type": {
						"type": "union",
						"types": [
							{
								"type": "literal",
								"value": null
							},
							{
								"type": "reference",
								"target": 9674,
								"name": "PriceList",
								"package": "@medusajs/pricing",
								"qualifiedName": "default"
							}
						]
					},
					"defaultValue": "null"
				},
				{
					"id": 9666,
					"name": "created_at",
					"variant": "declaration",
					"kind": 1024,
					"flags": {},
					"type": {
						"type": "reference",
						"target": {
							"sourceFileName": "../../node_modules/typescript/lib/lib.es5.d.ts",
							"qualifiedName": "Date"
						},
						"name": "Date",
						"package": "typescript"
					}
				},
				{
					"id": 9667,
					"name": "updated_at",
					"variant": "declaration",
					"kind": 1024,
					"flags": {},
					"type": {
						"type": "reference",
						"target": {
							"sourceFileName": "../../node_modules/typescript/lib/lib.es5.d.ts",
							"qualifiedName": "Date"
						},
						"name": "Date",
						"package": "typescript"
					}
				},
				{
					"id": 9668,
					"name": "deleted_at",
					"variant": "declaration",
					"kind": 1024,
					"flags": {},
					"type": {
						"type": "union",
						"types": [
							{
								"type": "literal",
								"value": null
							},
							{
								"type": "reference",
								"target": {
									"sourceFileName": "../../node_modules/typescript/lib/lib.es5.d.ts",
									"qualifiedName": "Date"
								},
								"name": "Date",
								"package": "typescript"
							}
						]
					},
					"defaultValue": "null"
				},
				{
					"id": 9669,
					"name": "onCreate",
					"variant": "declaration",
					"kind": 2048,
					"flags": {},
					"signatures": [
						{
							"id": 9670,
							"name": "onCreate",
							"variant": "signature",
							"kind": 4096,
							"flags": {},
							"type": {
								"type": "intrinsic",
								"name": "void"
							}
						}
					]
				},
				{
					"id": 9671,
					"name": "onInit",
					"variant": "declaration",
					"kind": 2048,
					"flags": {},
					"signatures": [
						{
							"id": 9672,
							"name": "onInit",
							"variant": "signature",
							"kind": 4096,
							"flags": {},
							"type": {
								"type": "intrinsic",
								"name": "void"
							}
						}
					]
				}
			],
			"groups": [
				{
					"title": "Constructors",
					"children": [
						9651
					]
				},
				{
					"title": "Properties",
					"children": [
						9673,
						9653,
						9654,
						9655,
						9656,
						9657,
						9658,
						9659,
						9660,
						9661,
						9662,
						9663,
						9664,
						9665,
						9666,
						9667,
						9668
					]
				},
				{
					"title": "Methods",
					"children": [
						9669,
						9671
					]
				}
			]
		}
	],
	"groups": [
		{
			"title": "Classes",
			"children": [
				9695,
				9674,
				9740,
				9711,
				9728,
				9650
			]
		}
	],
	"packageName": "@medusajs/pricing",
	"symbolIdMap": {
		"9649": {
			"sourceFileName": "../../../../packages/modules/pricing/src/models/index.ts",
			"qualifiedName": ""
		},
		"9650": {
			"sourceFileName": "../../../../packages/modules/pricing/src/models/price.ts",
			"qualifiedName": "default"
		},
		"9653": {
			"sourceFileName": "../../../../packages/modules/pricing/src/models/price.ts",
			"qualifiedName": "default.id"
		},
		"9654": {
			"sourceFileName": "../../../../packages/modules/pricing/src/models/price.ts",
			"qualifiedName": "default.title"
		},
		"9655": {
			"sourceFileName": "../../../../packages/modules/pricing/src/models/price.ts",
			"qualifiedName": "default.currency_code"
		},
		"9656": {
			"sourceFileName": "../../../../packages/modules/pricing/src/models/price.ts",
			"qualifiedName": "default.amount"
		},
		"9657": {
			"sourceFileName": "../../../../packages/modules/pricing/src/models/price.ts",
			"qualifiedName": "default.raw_amount"
		},
		"9658": {
			"sourceFileName": "../../../../packages/modules/pricing/src/models/price.ts",
			"qualifiedName": "default.min_quantity"
		},
		"9659": {
			"sourceFileName": "../../../../packages/modules/pricing/src/models/price.ts",
			"qualifiedName": "default.max_quantity"
		},
		"9660": {
			"sourceFileName": "../../../../packages/modules/pricing/src/models/price.ts",
			"qualifiedName": "default.price_set_id"
		},
		"9661": {
			"sourceFileName": "../../../../packages/modules/pricing/src/models/price.ts",
			"qualifiedName": "default.price_set"
		},
		"9662": {
			"sourceFileName": "../../../../packages/modules/pricing/src/models/price.ts",
			"qualifiedName": "default.rules_count"
		},
		"9663": {
			"sourceFileName": "../../../../packages/modules/pricing/src/models/price.ts",
			"qualifiedName": "default.price_rules"
		},
		"9664": {
			"sourceFileName": "../../../../packages/modules/pricing/src/models/price.ts",
			"qualifiedName": "default.price_list_id"
		},
		"9665": {
			"sourceFileName": "../../../../packages/modules/pricing/src/models/price.ts",
			"qualifiedName": "default.price_list"
		},
		"9666": {
			"sourceFileName": "../../../../packages/modules/pricing/src/models/price.ts",
			"qualifiedName": "default.created_at"
		},
		"9667": {
			"sourceFileName": "../../../../packages/modules/pricing/src/models/price.ts",
			"qualifiedName": "default.updated_at"
		},
		"9668": {
			"sourceFileName": "../../../../packages/modules/pricing/src/models/price.ts",
			"qualifiedName": "default.deleted_at"
		},
		"9669": {
			"sourceFileName": "../../../../packages/modules/pricing/src/models/price.ts",
			"qualifiedName": "default.onCreate"
		},
		"9670": {
			"sourceFileName": "../../../../packages/modules/pricing/src/models/price.ts",
			"qualifiedName": "default.onCreate"
		},
		"9671": {
			"sourceFileName": "../../../../packages/modules/pricing/src/models/price.ts",
			"qualifiedName": "default.onInit"
		},
		"9672": {
			"sourceFileName": "../../../../packages/modules/pricing/src/models/price.ts",
			"qualifiedName": "default.onInit"
		},
		"9673": {
			"sourceFileName": "../../../../packages/modules/pricing/src/models/price.ts",
			"qualifiedName": "default.[OptionalProps]"
		},
		"9674": {
			"sourceFileName": "../../../../packages/modules/pricing/src/models/price-list.ts",
			"qualifiedName": "default"
		},
		"9677": {
			"sourceFileName": "../../../../packages/modules/pricing/src/models/price-list.ts",
			"qualifiedName": "default.id"
		},
		"9678": {
			"sourceFileName": "../../../../packages/modules/pricing/src/models/price-list.ts",
			"qualifiedName": "default.title"
		},
		"9679": {
			"sourceFileName": "../../../../packages/modules/pricing/src/models/price-list.ts",
			"qualifiedName": "default.description"
		},
		"9680": {
			"sourceFileName": "../../../../packages/modules/pricing/src/models/price-list.ts",
			"qualifiedName": "default.status"
		},
		"9681": {
			"sourceFileName": "../../../../packages/modules/pricing/src/models/price-list.ts",
			"qualifiedName": "default.type"
		},
		"9682": {
			"sourceFileName": "../../../../packages/modules/pricing/src/models/price-list.ts",
			"qualifiedName": "default.starts_at"
		},
		"9683": {
			"sourceFileName": "../../../../packages/modules/pricing/src/models/price-list.ts",
			"qualifiedName": "default.ends_at"
		},
		"9684": {
			"sourceFileName": "../../../../packages/modules/pricing/src/models/price-list.ts",
			"qualifiedName": "default.prices"
		},
		"9685": {
			"sourceFileName": "../../../../packages/modules/pricing/src/models/price-list.ts",
			"qualifiedName": "default.price_list_rules"
		},
		"9686": {
			"sourceFileName": "../../../../packages/modules/pricing/src/models/price-list.ts",
			"qualifiedName": "default.rules_count"
		},
		"9687": {
			"sourceFileName": "../../../../packages/modules/pricing/src/models/price-list.ts",
			"qualifiedName": "default.created_at"
		},
		"9688": {
			"sourceFileName": "../../../../packages/modules/pricing/src/models/price-list.ts",
			"qualifiedName": "default.updated_at"
		},
		"9689": {
			"sourceFileName": "../../../../packages/modules/pricing/src/models/price-list.ts",
			"qualifiedName": "default.deleted_at"
		},
		"9690": {
			"sourceFileName": "../../../../packages/modules/pricing/src/models/price-list.ts",
			"qualifiedName": "default.onCreate"
		},
		"9691": {
			"sourceFileName": "../../../../packages/modules/pricing/src/models/price-list.ts",
			"qualifiedName": "default.onCreate"
		},
		"9692": {
			"sourceFileName": "../../../../packages/modules/pricing/src/models/price-list.ts",
			"qualifiedName": "default.onInit"
		},
		"9693": {
			"sourceFileName": "../../../../packages/modules/pricing/src/models/price-list.ts",
			"qualifiedName": "default.onInit"
		},
		"9694": {
			"sourceFileName": "../../../../packages/modules/pricing/src/models/price-list.ts",
			"qualifiedName": "default.[OptionalProps]"
		},
		"9695": {
			"sourceFileName": "../../../../packages/modules/pricing/src/models/price-list-rule.ts",
			"qualifiedName": "default"
		},
		"9698": {
			"sourceFileName": "../../../../packages/modules/pricing/src/models/price-list-rule.ts",
			"qualifiedName": "default.id"
		},
		"9699": {
			"sourceFileName": "../../../../packages/modules/pricing/src/models/price-list-rule.ts",
			"qualifiedName": "default.attribute"
		},
		"9700": {
			"sourceFileName": "../../../../packages/modules/pricing/src/models/price-list-rule.ts",
			"qualifiedName": "default.value"
		},
		"9701": {
			"sourceFileName": "../../../../packages/modules/pricing/src/models/price-list-rule.ts",
			"qualifiedName": "default.price_list_id"
		},
		"9702": {
			"sourceFileName": "../../../../packages/modules/pricing/src/models/price-list-rule.ts",
			"qualifiedName": "default.price_list"
		},
		"9703": {
			"sourceFileName": "../../../../packages/modules/pricing/src/models/price-list-rule.ts",
			"qualifiedName": "default.created_at"
		},
		"9704": {
			"sourceFileName": "../../../../packages/modules/pricing/src/models/price-list-rule.ts",
			"qualifiedName": "default.updated_at"
		},
		"9705": {
			"sourceFileName": "../../../../packages/modules/pricing/src/models/price-list-rule.ts",
			"qualifiedName": "default.deleted_at"
		},
		"9706": {
			"sourceFileName": "../../../../packages/modules/pricing/src/models/price-list-rule.ts",
			"qualifiedName": "default.beforeCreate"
		},
		"9707": {
			"sourceFileName": "../../../../packages/modules/pricing/src/models/price-list-rule.ts",
			"qualifiedName": "default.beforeCreate"
		},
		"9708": {
			"sourceFileName": "../../../../packages/modules/pricing/src/models/price-list-rule.ts",
			"qualifiedName": "default.onInit"
		},
		"9709": {
			"sourceFileName": "../../../../packages/modules/pricing/src/models/price-list-rule.ts",
			"qualifiedName": "default.onInit"
		},
		"9710": {
			"sourceFileName": "../../../../packages/modules/pricing/src/models/price-list-rule.ts",
			"qualifiedName": "default.[OptionalProps]"
		},
		"9711": {
			"sourceFileName": "../../../../packages/modules/pricing/src/models/price-rule.ts",
			"qualifiedName": "default"
		},
		"9714": {
			"sourceFileName": "../../../../packages/modules/pricing/src/models/price-rule.ts",
			"qualifiedName": "default.id"
		},
		"9715": {
			"sourceFileName": "../../../../packages/modules/pricing/src/models/price-rule.ts",
			"qualifiedName": "default.attribute"
		},
		"9716": {
			"sourceFileName": "../../../../packages/modules/pricing/src/models/price-rule.ts",
			"qualifiedName": "default.value"
		},
		"9717": {
			"sourceFileName": "../../../../packages/modules/pricing/src/models/price-rule.ts",
			"qualifiedName": "default.priority"
		},
		"9718": {
			"sourceFileName": "../../../../packages/modules/pricing/src/models/price-rule.ts",
			"qualifiedName": "default.price_id"
		},
		"9719": {
			"sourceFileName": "../../../../packages/modules/pricing/src/models/price-rule.ts",
			"qualifiedName": "default.price"
		},
		"9720": {
			"sourceFileName": "../../../../packages/modules/pricing/src/models/price-rule.ts",
			"qualifiedName": "default.created_at"
		},
		"9721": {
			"sourceFileName": "../../../../packages/modules/pricing/src/models/price-rule.ts",
			"qualifiedName": "default.updated_at"
		},
		"9722": {
			"sourceFileName": "../../../../packages/modules/pricing/src/models/price-rule.ts",
			"qualifiedName": "default.deleted_at"
		},
		"9723": {
			"sourceFileName": "../../../../packages/modules/pricing/src/models/price-rule.ts",
			"qualifiedName": "default.beforeCreate"
		},
		"9724": {
			"sourceFileName": "../../../../packages/modules/pricing/src/models/price-rule.ts",
			"qualifiedName": "default.beforeCreate"
		},
		"9725": {
			"sourceFileName": "../../../../packages/modules/pricing/src/models/price-rule.ts",
			"qualifiedName": "default.onInit"
		},
		"9726": {
			"sourceFileName": "../../../../packages/modules/pricing/src/models/price-rule.ts",
			"qualifiedName": "default.onInit"
		},
		"9727": {
			"sourceFileName": "../../../../packages/modules/pricing/src/models/price-rule.ts",
			"qualifiedName": "default.[OptionalProps]"
		},
		"9728": {
			"sourceFileName": "../../../../packages/modules/pricing/src/models/price-set.ts",
			"qualifiedName": "default"
		},
		"9731": {
			"sourceFileName": "../../../../packages/modules/pricing/src/models/price-set.ts",
			"qualifiedName": "default.id"
		},
		"9732": {
			"sourceFileName": "../../../../packages/modules/pricing/src/models/price-set.ts",
			"qualifiedName": "default.prices"
		},
		"9733": {
			"sourceFileName": "../../../../packages/modules/pricing/src/models/price-set.ts",
			"qualifiedName": "default.created_at"
		},
		"9734": {
			"sourceFileName": "../../../../packages/modules/pricing/src/models/price-set.ts",
			"qualifiedName": "default.updated_at"
		},
		"9735": {
			"sourceFileName": "../../../../packages/modules/pricing/src/models/price-set.ts",
			"qualifiedName": "default.deleted_at"
		},
		"9736": {
			"sourceFileName": "../../../../packages/modules/pricing/src/models/price-set.ts",
			"qualifiedName": "default.onCreate"
		},
		"9737": {
			"sourceFileName": "../../../../packages/modules/pricing/src/models/price-set.ts",
			"qualifiedName": "default.onCreate"
		},
		"9738": {
			"sourceFileName": "../../../../packages/modules/pricing/src/models/price-set.ts",
			"qualifiedName": "default.onInit"
		},
		"9739": {
			"sourceFileName": "../../../../packages/modules/pricing/src/models/price-set.ts",
			"qualifiedName": "default.onInit"
		},
		"9740": {
			"sourceFileName": "../../../../packages/modules/pricing/src/models/price-preference.ts",
			"qualifiedName": "default"
		},
		"9743": {
			"sourceFileName": "../../../../packages/modules/pricing/src/models/price-preference.ts",
			"qualifiedName": "default.id"
		},
		"9744": {
			"sourceFileName": "../../../../packages/modules/pricing/src/models/price-preference.ts",
			"qualifiedName": "default.attribute"
		},
		"9745": {
			"sourceFileName": "../../../../packages/modules/pricing/src/models/price-preference.ts",
			"qualifiedName": "default.value"
		},
		"9746": {
			"sourceFileName": "../../../../packages/modules/pricing/src/models/price-preference.ts",
			"qualifiedName": "default.is_tax_inclusive"
		},
		"9747": {
			"sourceFileName": "../../../../packages/modules/pricing/src/models/price-preference.ts",
			"qualifiedName": "default.created_at"
		},
		"9748": {
			"sourceFileName": "../../../../packages/modules/pricing/src/models/price-preference.ts",
			"qualifiedName": "default.updated_at"
		},
		"9749": {
			"sourceFileName": "../../../../packages/modules/pricing/src/models/price-preference.ts",
			"qualifiedName": "default.deleted_at"
		},
		"9750": {
			"sourceFileName": "../../../../packages/modules/pricing/src/models/price-preference.ts",
			"qualifiedName": "default.onCreate"
		},
		"9751": {
			"sourceFileName": "../../../../packages/modules/pricing/src/models/price-preference.ts",
			"qualifiedName": "default.onCreate"
		},
		"9752": {
			"sourceFileName": "../../../../packages/modules/pricing/src/models/price-preference.ts",
			"qualifiedName": "default.onInit"
		},
		"9753": {
			"sourceFileName": "../../../../packages/modules/pricing/src/models/price-preference.ts",
			"qualifiedName": "default.onInit"
		}
	},
	"files": {
		"entries": {
			"1": "../../../../packages/modules/pricing/src/models/index.ts"
		},
		"reflections": {
			"1": 9649
		}
	}
}