{
  "namespaces": [
    "public"
  ],
  "name": "public",
  "tables": [
    {
      "columns": {
        "id": {
          "name": "id",
          "type": "text",
          "unsigned": false,
          "autoincrement": false,
          "primary": false,
          "nullable": false,
          "mappedType": "text"
        },
        "company_name": {
          "name": "company_name",
          "type": "text",
          "unsigned": false,
          "autoincrement": false,
          "primary": false,
          "nullable": true,
          "mappedType": "text"
        },
        "first_name": {
          "name": "first_name",
          "type": "text",
          "unsigned": false,
          "autoincrement": false,
          "primary": false,
          "nullable": true,
          "mappedType": "text"
        },
        "last_name": {
          "name": "last_name",
          "type": "text",
          "unsigned": false,
          "autoincrement": false,
          "primary": false,
          "nullable": true,
          "mappedType": "text"
        },
        "email": {
          "name": "email",
          "type": "text",
          "unsigned": false,
          "autoincrement": false,
          "primary": false,
          "nullable": true,
          "mappedType": "text"
        },
        "phone": {
          "name": "phone",
          "type": "text",
          "unsigned": false,
          "autoincrement": false,
          "primary": false,
          "nullable": true,
          "mappedType": "text"
        },
        "has_account": {
          "name": "has_account",
          "type": "boolean",
          "unsigned": false,
          "autoincrement": false,
          "primary": false,
          "nullable": false,
          "default": "false",
          "mappedType": "boolean"
        },
        "metadata": {
          "name": "metadata",
          "type": "jsonb",
          "unsigned": false,
          "autoincrement": false,
          "primary": false,
          "nullable": true,
          "mappedType": "json"
        },
        "created_at": {
          "name": "created_at",
          "type": "timestamptz",
          "unsigned": false,
          "autoincrement": false,
          "primary": false,
          "nullable": false,
          "length": 6,
          "default": "now()",
          "mappedType": "datetime"
        },
        "updated_at": {
          "name": "updated_at",
          "type": "timestamptz",
          "unsigned": false,
          "autoincrement": false,
          "primary": false,
          "nullable": false,
          "length": 6,
          "default": "now()",
          "mappedType": "datetime"
        },
        "deleted_at": {
          "name": "deleted_at",
          "type": "timestamptz",
          "unsigned": false,
          "autoincrement": false,
          "primary": false,
          "nullable": true,
          "length": 6,
          "mappedType": "datetime"
        },
        "created_by": {
          "name": "created_by",
          "type": "text",
          "unsigned": false,
          "autoincrement": false,
          "primary": false,
          "nullable": true,
          "mappedType": "text"
        }
      },
      "name": "customer",
      "schema": "public",
      "indexes": [
        {
          "keyName": "IDX_customer_email_unique",
          "columnNames": [],
          "composite": false,
          "primary": false,
          "unique": false,
          "expression": "CREATE UNIQUE INDEX IF NOT EXISTS \"IDX_customer_email_unique\" ON \"customer\" (email) WHERE deleted_at IS NULL"
        },
        {
          "keyName": "customer_pkey",
          "columnNames": [
            "id"
          ],
          "composite": false,
          "primary": true,
          "unique": true
        }
      ],
      "checks": [],
      "foreignKeys": {}
    },
    {
      "columns": {
        "id": {
          "name": "id",
          "type": "text",
          "unsigned": false,
          "autoincrement": false,
          "primary": false,
          "nullable": false,
          "mappedType": "text"
        },
        "address_name": {
          "name": "address_name",
          "type": "text",
          "unsigned": false,
          "autoincrement": false,
          "primary": false,
          "nullable": true,
          "mappedType": "text"
        },
        "is_default_shipping": {
          "name": "is_default_shipping",
          "type": "boolean",
          "unsigned": false,
          "autoincrement": false,
          "primary": false,
          "nullable": false,
          "default": "false",
          "mappedType": "boolean"
        },
        "is_default_billing": {
          "name": "is_default_billing",
          "type": "boolean",
          "unsigned": false,
          "autoincrement": false,
          "primary": false,
          "nullable": false,
          "default": "false",
          "mappedType": "boolean"
        },
        "customer_id": {
          "name": "customer_id",
          "type": "text",
          "unsigned": false,
          "autoincrement": false,
          "primary": false,
          "nullable": false,
          "mappedType": "text"
        },
        "company": {
          "name": "company",
          "type": "text",
          "unsigned": false,
          "autoincrement": false,
          "primary": false,
          "nullable": true,
          "mappedType": "text"
        },
        "first_name": {
          "name": "first_name",
          "type": "text",
          "unsigned": false,
          "autoincrement": false,
          "primary": false,
          "nullable": true,
          "mappedType": "text"
        },
        "last_name": {
          "name": "last_name",
          "type": "text",
          "unsigned": false,
          "autoincrement": false,
          "primary": false,
          "nullable": true,
          "mappedType": "text"
        },
        "address_1": {
          "name": "address_1",
          "type": "text",
          "unsigned": false,
          "autoincrement": false,
          "primary": false,
          "nullable": true,
          "mappedType": "text"
        },
        "address_2": {
          "name": "address_2",
          "type": "text",
          "unsigned": false,
          "autoincrement": false,
          "primary": false,
          "nullable": true,
          "mappedType": "text"
        },
        "city": {
          "name": "city",
          "type": "text",
          "unsigned": false,
          "autoincrement": false,
          "primary": false,
          "nullable": true,
          "mappedType": "text"
        },
        "country_code": {
          "name": "country_code",
          "type": "text",
          "unsigned": false,
          "autoincrement": false,
          "primary": false,
          "nullable": true,
          "mappedType": "text"
        },
        "province": {
          "name": "province",
          "type": "text",
          "unsigned": false,
          "autoincrement": false,
          "primary": false,
          "nullable": true,
          "mappedType": "text"
        },
        "postal_code": {
          "name": "postal_code",
          "type": "text",
          "unsigned": false,
          "autoincrement": false,
          "primary": false,
          "nullable": true,
          "mappedType": "text"
        },
        "phone": {
          "name": "phone",
          "type": "text",
          "unsigned": false,
          "autoincrement": false,
          "primary": false,
          "nullable": true,
          "mappedType": "text"
        },
        "metadata": {
          "name": "metadata",
          "type": "jsonb",
          "unsigned": false,
          "autoincrement": false,
          "primary": false,
          "nullable": true,
          "mappedType": "json"
        },
        "created_at": {
          "name": "created_at",
          "type": "timestamptz",
          "unsigned": false,
          "autoincrement": false,
          "primary": false,
          "nullable": false,
          "length": 6,
          "default": "now()",
          "mappedType": "datetime"
        },
        "updated_at": {
          "name": "updated_at",
          "type": "timestamptz",
          "unsigned": false,
          "autoincrement": false,
          "primary": false,
          "nullable": false,
          "length": 6,
          "default": "now()",
          "mappedType": "datetime"
        }
      },
      "name": "customer_address",
      "schema": "public",
      "indexes": [
        {
          "columnNames": [
            "customer_id"
          ],
          "composite": false,
          "keyName": "IDX_customer_address_customer_id",
          "primary": false,
          "unique": false
        },
        {
          "keyName": "IDX_customer_address_customer_id",
          "columnNames": [],
          "composite": false,
          "primary": false,
          "unique": false,
          "expression": "CREATE INDEX IF NOT EXISTS \"IDX_customer_address_customer_id\" ON \"customer_address\" (customer_id) WHERE \"is_default_billing\" = true"
        },
        {
          "keyName": "IDX_customer_address_customer_id",
          "columnNames": [],
          "composite": false,
          "primary": false,
          "unique": false,
          "expression": "CREATE INDEX IF NOT EXISTS \"IDX_customer_address_customer_id\" ON \"customer_address\" (customer_id) WHERE \"is_default_shipping\" = true"
        },
        {
          "keyName": "customer_address_pkey",
          "columnNames": [
            "id"
          ],
          "composite": false,
          "primary": true,
          "unique": true
        }
      ],
      "checks": [],
      "foreignKeys": {
        "customer_address_customer_id_foreign": {
          "constraintName": "customer_address_customer_id_foreign",
          "columnNames": [
            "customer_id"
          ],
          "localTableName": "public.customer_address",
          "referencedColumnNames": [
            "id"
          ],
          "referencedTableName": "public.customer",
          "deleteRule": "cascade",
          "updateRule": "cascade"
        }
      }
    },
    {
      "columns": {
        "id": {
          "name": "id",
          "type": "text",
          "unsigned": false,
          "autoincrement": false,
          "primary": false,
          "nullable": false,
          "mappedType": "text"
        },
        "name": {
          "name": "name",
          "type": "text",
          "unsigned": false,
          "autoincrement": false,
          "primary": false,
          "nullable": true,
          "mappedType": "text"
        },
        "metadata": {
          "name": "metadata",
          "type": "jsonb",
          "unsigned": false,
          "autoincrement": false,
          "primary": false,
          "nullable": true,
          "mappedType": "json"
        },
        "created_by": {
          "name": "created_by",
          "type": "text",
          "unsigned": false,
          "autoincrement": false,
          "primary": false,
          "nullable": true,
          "mappedType": "text"
        },
        "created_at": {
          "name": "created_at",
          "type": "timestamptz",
          "unsigned": false,
          "autoincrement": false,
          "primary": false,
          "nullable": false,
          "length": 6,
          "default": "now()",
          "mappedType": "datetime"
        },
        "updated_at": {
          "name": "updated_at",
          "type": "timestamptz",
          "unsigned": false,
          "autoincrement": false,
          "primary": false,
          "nullable": false,
          "length": 6,
          "default": "now()",
          "mappedType": "datetime"
        },
        "deleted_at": {
          "name": "deleted_at",
          "type": "timestamptz",
          "unsigned": false,
          "autoincrement": false,
          "primary": false,
          "nullable": true,
          "length": 6,
          "mappedType": "datetime"
        }
      },
      "name": "customer_group",
      "schema": "public",
      "indexes": [
        {
          "keyName": "customer_group_pkey",
          "columnNames": [
            "id"
          ],
          "composite": false,
          "primary": true,
          "unique": true
        }
      ],
      "checks": [],
      "foreignKeys": {}
    },
    {
      "columns": {
        "id": {
          "name": "id",
          "type": "text",
          "unsigned": false,
          "autoincrement": false,
          "primary": false,
          "nullable": false,
          "mappedType": "text"
        },
        "customer_id": {
          "name": "customer_id",
          "type": "text",
          "unsigned": false,
          "autoincrement": false,
          "primary": false,
          "nullable": false,
          "mappedType": "text"
        },
        "customer_group_id": {
          "name": "customer_group_id",
          "type": "text",
          "unsigned": false,
          "autoincrement": false,
          "primary": false,
          "nullable": false,
          "mappedType": "text"
        },
        "metadata": {
          "name": "metadata",
          "type": "jsonb",
          "unsigned": false,
          "autoincrement": false,
          "primary": false,
          "nullable": true,
          "mappedType": "json"
        },
        "created_at": {
          "name": "created_at",
          "type": "timestamptz",
          "unsigned": false,
          "autoincrement": false,
          "primary": false,
          "nullable": false,
          "length": 6,
          "default": "now()",
          "mappedType": "datetime"
        },
        "updated_at": {
          "name": "updated_at",
          "type": "timestamptz",
          "unsigned": false,
          "autoincrement": false,
          "primary": false,
          "nullable": false,
          "length": 6,
          "default": "now()",
          "mappedType": "datetime"
        },
        "created_by": {
          "name": "created_by",
          "type": "text",
          "unsigned": false,
          "autoincrement": false,
          "primary": false,
          "nullable": true,
          "mappedType": "text"
        }
      },
      "name": "customer_group_customer",
      "schema": "public",
      "indexes": [
        {
          "columnNames": [
            "customer_group_id"
          ],
          "composite": false,
          "keyName": "IDX_customer_group_customer_group_id",
          "primary": false,
          "unique": false
        },
        {
          "columnNames": [
            "customer_id"
          ],
          "composite": false,
          "keyName": "IDX_customer_group_customer_customer_id",
          "primary": false,
          "unique": false
        },
        {
          "keyName": "customer_group_customer_pkey",
          "columnNames": [
            "id"
          ],
          "composite": false,
          "primary": true,
          "unique": true
        }
      ],
      "checks": [],
      "foreignKeys": {
        "customer_group_customer_customer_group_id_foreign": {
          "constraintName": "customer_group_customer_customer_group_id_foreign",
          "columnNames": [
            "customer_group_id"
          ],
          "localTableName": "public.customer_group_customer",
          "referencedColumnNames": [
            "id"
          ],
          "referencedTableName": "public.customer_group",
          "deleteRule": "cascade"
        },
        "customer_group_customer_customer_id_foreign": {
          "constraintName": "customer_group_customer_customer_id_foreign",
          "columnNames": [
            "customer_id"
          ],
          "localTableName": "public.customer_group_customer",
          "referencedColumnNames": [
            "id"
          ],
          "referencedTableName": "public.customer",
          "deleteRule": "cascade"
        }
      }
    }
  ]
}
